Workbook

Sheet Quick Screen
B2: QUICK SCREEN — SPONSOR CASH FLOW
B6: Input the main data available | G6: <<<<<<<< | H6: This is just a simplistic and fast way to determine the margin of the developer to understand if it's a viable operation
B8: Buildable Area | D8: Sqm
B10: Sponsor Cash Flow | C10: € | D10: €/sqm
B11: (+) Sale Proceeds | C11: =Inputs!C18 -> 0 | D11: =IFERROR(C11/$C$8,0) -> 0
B12: (−) Acquisition Cost | C12: =-Inputs!D23*(1+Inputs!D24) -> 0 | D12: =IFERROR(C12/$C$8,0) -> 0
B13: Acquisition Price | C13: =-Inputs!D23 -> 0 | D13: =IFERROR(C13/$C$8,0) -> 0
B14: Related Costs | C14: =-Inputs!D23*Inputs!D24 -> 0 | D14: =IFERROR(C14/$C$8,0) -> 0
B15: (−) Construction Works | C15: =-(Inputs!D29*Inputs!C15+Inputs!D28*Inputs!C15+(Inputs!D29*Inputs!C15+Inputs!D28*Inputs!C15)*Inputs!D30) -> 0 | D15: =IFERROR(C15/$C$8,0) -> 0
B16: Soft Costs (excl. PM) | C16: =-Inputs!D29*Inputs!C15 -> 0 | D16: =IFERROR(C16/$C$8,0) -> 0
B17: Hard Costs | C17: =-Inputs!D28*Inputs!C15 -> 0 | D17: =IFERROR(C17/$C$8,0) -> 0
B18: Project Management (PM) | C18: =-(Inputs!D29*Inputs!C15+Inputs!D28*Inputs!C15)*Inputs!D30 -> 0 | D18: =IFERROR(C18/$C$8,0) -> 0
B19: (−) Other Costs | C19: =-Inputs!D31 -> 0 | D19: =IFERROR(C19/$C$8,0) -> 0
B20: Sponsor Margin | C20: =C11+C12+C15+C19 -> 0 | D20: =IFERROR(C20/C11,0) -> 0
B21: PIK Interests + Opening Fee | C21: =-('Cash Flow'!C11+'Cash Flow'!C12) -> #REF! | D21: =IFERROR(C21/$C$8,0) -> 0
B22: Sponsor Net Margin | C22: =C20+C21 -> #REF! | D22: =+IFERROR(C22/C11,0) -> 0

Sheet Cover
B2: CLIKALIA DEBT FUND — UNDERWRITING MODEL
B3: Senior Secured Bridge Loan — Residential Development — Spain
B5: DEAL IDENTIFICATION
B7: Project Name | C7: 0
B8: Sponsor | C8: 0
B9: Borrower SPV | C9: 0
B10: Location (City, Province) | C10: 0
B11: Product Type | C11: 0
B12: Total Buildable Area (sqm) | C12: 0
B13: Total Units | C13: 0
B14: Deal Date | C14: =TODAY() -> 46133
B15: Underwriter | C15: 0
B17: LOAN HEADLINE
B19: Loan Commitment (€) | C19: 0
B20: LTC (Loan / Total Cost) | C20: 0
B21: LTV (Loan / GDV) | C21: 0
B22: Peak Loan Balance (€) | C22: 0
B23: PIK Rate | C23: 0
B24: Opening Fee | C24: 0
B25: Duration | C25: 0

Sheet Inputs
B2: INPUTS
B4: 0. GENERAL ASSUMPTIONS
D6: Duration
B7: Model start Date | C7: =+EOMONTH(F7,D7) -> 46599 | D7: 15 | E7: Today | F7: =+TODAY() -> 46133
B8: Model End Date | C8: =+EOMONTH(C7,D7) -> 47057
B13: 1. SALES PLAN
B15: Buildable area (sqm)
B16: Number of units
B17: Average sale price (€/sqm)
B18: Sale € | C18: =C15*C17 -> 0
B20: 2. COSTS
C22: Total € | D22: €/sqm | E22: %
B23: Acquisition price (€) | C23: =+IFERROR(D23*$C$15,0) -> 0
B24: Related acquisition costs (% of acq. price) | C24: =+IFERROR(E24*$C$23,0) -> 0 | D24: =+IFERROR(C24/$C$15,0) -> 0 | E24: 0
B25: Notary | C25: =+IFERROR(E25*$C$23,0) -> 0 | D25: =+IFERROR(C25/$C$15,0) -> 0 | E25: 0
B26: AJD | C26: =+IFERROR(E26*$C$23,0) -> 0 | D26: =+IFERROR(C26/$C$15,0) -> 0 | E26: 0
B27: Other costs (%,Variables) | C27: =+IFERROR(E27*$C$23,0) -> 0 | D27: =+IFERROR(C27/$C$15,0) -> 0 | E27: 0
B28: Hard costs (€/sqm) | C28: =+IFERROR(D28*$C$15,0) -> 0
B29: Soft costs (€/sqm) | C29: =+IFERROR(D29*$C$15,0) -> 0
B30: Project management (% of hard + soft) | C30: =+IFERROR(SUM(C28:C29)*E30,0) -> 0 | D30: =+IFERROR(C30/C15,0) -> 0 | E30: 0
B31: Other costs (€, fixed) | D31: =+IFERROR(C31/$C$15,0) -> 0
B33: 2b. COST DETAIL (optional — for reference only)
B35: Hard costs detail | C35: Total € | D35: €/sqm
B36: Structure & shell
B37: MEP (mechanical/electrical/plumbing)
B38: Finishes
B39: External works
B40: Contingency
B41: Total hard costs (detail sum) — €/sqm | C41: =SUM(C36:C40) -> 0 | D41: =SUM(D36:D40) -> 0
B42: Delta vs. aggregate | C42: =C41-C28 -> 0 | D42: =D41-D28 -> 0
B44: Soft costs detail | C44: Total € | D44: €/sqm
B45: Architectural & engineering fees
B46: Licensing & permits
B47: Insurance (all-risk construction)
B48: Legal & consultancy
B49: Total soft costs (detail sum) — €/sqm | C49: =SUM(C45:C48) -> 0 | D49: =SUM(D45:D48) -> 0
B50: Delta vs. aggregate | C50: =C49-C29 -> 0 | D50: =D49-D29 -> 0
B52: 3. FINANCING TERMS
C54: Total € | D54: €/sqm
B55: Loan commitment (€)
B56: Duration (months)
B57: PIK rate (% annual)
B58: Opening fee (%)
B60: 4. TIMING (Project Phasing)
I61: 1 | J61: =+I61+1 -> 2 | K61: =+J61+1 -> 3 | L61: =+K61+1 -> 4 | M61: =+L61+1 -> 5 | N61: =+M61+1 -> 6 | O61: =+N61+1 -> 7 | P61: =+O61+1 -> 8 | Q61: =+P61+1 -> 9 | ... CT61: =+CS61+1 -> 90
I62: =+C7 -> 46599 | J62: =+EOMONTH(I62,1) -> 46630 | K62: =+EOMONTH(J62,1) -> 46660 | L62: =+EOMONTH(K62,1) -> 46691 | M62: =+EOMONTH(L62,1) -> 46721 | N62: =+EOMONTH(M62,1) -> 46752 | O62: =+EOMONTH(N62,1) -> 46783 | P62: =+EOMONTH(O62,1) -> 46812 | Q62: =+EOMONTH(P62,1) -> 46843 | ... CT62: =+EOMONTH(CS62,1) -> 49309
C64: Starting month/date | D64: Duration | E64: End Date
B65: Acquisition / licensing duration (months) | C65: 1 | D65: 5 | E65: =+D65+C65 -> 6
B66: Construction duration (months) | C66: =+E65 -> 6 | D66: 5 | E66: =+D66+C66 -> 11
B67: Sales start offset from construction start (months) | C67: =+E66 -> 11 | D67: 5 | E67: =+D67+C67 -> 16
B68: Sales window duration (months) | C68: =+E67 -> 16 | D68: 5 | E68: =+D68+C68 -> 21
B71: 5. SALES PAYMENT SCHEDULE (Reservation Profile)
C73: Total € | D73: €/sqm
B74: % collected at reservation (pre-sale signing)
B75: % collected during construction (progress payments)
B76: % collected at delivery (escritura)
B77: Delivery offset after construction end (months)
B78: Check: should sum to 100% | C78: =C74+C75+C76 -> 0 | D78: =D74+D75+D76 -> 0

Sheet Cash Flow
A1: CASH FLOW — MONTHLY (Lender View)
B4: LENDER VIEW — KEY METRICS
B5: Loan Commitment | C5: =Inputs!D55 -> 0
B6: Cumulative Draws (gross) | C6: =SUM(H73:BO73)+SUM(H72:BO72) -> 0
B7: Peak Loan Balance | C7: =MAX(H76:BO76) -> #REF!
B8: Month of Peak | C8: =MATCH(C7,H76:BO76,0) -> #REF!
B9: Funding Life (months) | C9: =COUNTIF(H76:BO76,">=1") -> 0
B10: Cumulative Repayments | C10: =SUM(H75:BO75) -> #REF!
B11: Total PIK Interest | C11: =SUM(H74:BO74) -> #REF!
B12: Opening Fee | C12: =SUM(H72:BO72) -> 0
B14: P&L (MONTHLY)
B15: Line | C15: Total | H15: =H45 -> 46142 | I15: =I45 -> 46173 | J15: =J45 -> 46203 | K15: =K45 -> 46234 | L15: =L45 -> 46265 | M15: =M45 -> 46295 | N15: =N45 -> 46326 | O15: =O45 -> 46356 | ... BO15: =BO45 -> 47938
B16: Revenues (sale proceeds) | C16: =SUM(H16:BO16) -> 0 | H16: =H55 -> 0 | I16: =I55 -> 0 | J16: =J55 -> 0 | K16: =K55 -> 0 | L16: =L55 -> 0 | M16: =M55 -> 0 | N16: =N55 -> 0 | O16: =O55 -> 0 | ... BO16: =BO55 -> 0
B18: Acquisition cost | C18: =SUM(H18:BO18) -> 0 | H18: =-H48 -> 0 | I18: =-I48 -> 0 | J18: =-J48 -> 0 | K18: =-K48 -> 0 | L18: =-L48 -> 0 | M18: =-M48 -> 0 | N18: =-N48 -> 0 | O18: =-O48 -> 0 | ... BO18: =-BO48 -> 0
B19: Hard costs | C19: =SUM(H19:BO19) -> 0 | H19: =-IF(AND(H$44>Inputs!$D$65,H$44<=Inputs!$D$65+Inputs!$D$66,Inputs!$D$66>0),Inputs!$D$28*Inputs!$C$15/Inputs!$D$66,0) -> 0 | I19: =-IF(AND(I$44>Inputs!$D$65,I$44<=Inputs!$D$65+Inputs!$D$66,Inputs!$D$66>0),Inputs!$D$28*Inputs!$C$15/Inputs!$D$66,0) -> 0 | J19: =-IF(AND(J$44>Inputs!$D$65,J$44<=Inputs!$D$65+Inputs!$D$66,Inputs!$D$66>0),Inputs!$D$28*Inputs!$C$15/Inputs!$D$66,0) -> 0 | K19: =-IF(AND(K$44>Inputs!$D$65,K$44<=Inputs!$D$65+Inputs!$D$66,Inputs!$D$66>0),Inputs!$D$28*Inputs!$C$15/Inputs!$D$66,0) -> 0 | L19: =-IF(AND(L$44>Inputs!$D$65,L$44<=Inputs!$D$65+Inputs!$D$66,Inputs!$D$66>0),Inputs!$D$28*Inputs!$C$15/Inputs!$D$66,0) -> 0 | M19: =-IF(AND(M$44>Inputs!$D$65,M$44<=Inputs!$D$65+Inputs!$D$66,Inputs!$D$66>0),Inputs!$D$28*Inputs!$C$15/Inputs!$D$66,0) -> 0 | N19: =-IF(AND(N$44>Inputs!$D$65,N$44<=Inputs!$D$65+Inputs!$D$66,Inputs!$D$66>0),Inputs!$D$28*Inputs!$C$15/Inputs!$D$66,0) -> 0 | O19: =-IF(AND(O$44>Inputs!$D$65,O$44<=Inputs!$D$65+Inputs!$D$66,Inputs!$D$66>0),Inputs!$D$28*Inputs!$C$15/Inputs!$D$66,0) -> 0 | ... BO19: =-IF(AND(BO$44>Inputs!$D$65,BO$44<=Inputs!$D$65+Inputs!$D$66,Inputs!$D$66>0),Inputs!$D$28*Inputs!$C$15/Inputs!$D$66,0) -> 0
B20: Soft costs | C20: =SUM(H20:BO20) -> 0 | H20: =-IF(AND(H$44>Inputs!$D$65,H$44<=Inputs!$D$65+Inputs!$D$66,Inputs!$D$66>0),Inputs!$D$29*Inputs!$C$15/Inputs!$D$66,0) -> 0 | I20: =-IF(AND(I$44>Inputs!$D$65,I$44<=Inputs!$D$65+Inputs!$D$66,Inputs!$D$66>0),Inputs!$D$29*Inputs!$C$15/Inputs!$D$66,0) -> 0 | J20: =-IF(AND(J$44>Inputs!$D$65,J$44<=Inputs!$D$65+Inputs!$D$66,Inputs!$D$66>0),Inputs!$D$29*Inputs!$C$15/Inputs!$D$66,0) -> 0 | K20: =-IF(AND(K$44>Inputs!$D$65,K$44<=Inputs!$D$65+Inputs!$D$66,Inputs!$D$66>0),Inputs!$D$29*Inputs!$C$15/Inputs!$D$66,0) -> 0 | L20: =-IF(AND(L$44>Inputs!$D$65,L$44<=Inputs!$D$65+Inputs!$D$66,Inputs!$D$66>0),Inputs!$D$29*Inputs!$C$15/Inputs!$D$66,0) -> 0 | M20: =-IF(AND(M$44>Inputs!$D$65,M$44<=Inputs!$D$65+Inputs!$D$66,Inputs!$D$66>0),Inputs!$D$29*Inputs!$C$15/Inputs!$D$66,0) -> 0 | N20: =-IF(AND(N$44>Inputs!$D$65,N$44<=Inputs!$D$65+Inputs!$D$66,Inputs!$D$66>0),Inputs!$D$29*Inputs!$C$15/Inputs!$D$66,0) -> 0 | O20: =-IF(AND(O$44>Inputs!$D$65,O$44<=Inputs!$D$65+Inputs!$D$66,Inputs!$D$66>0),Inputs!$D$29*Inputs!$C$15/Inputs!$D$66,0) -> 0 | ... BO20: =-IF(AND(BO$44>Inputs!$D$65,BO$44<=Inputs!$D$65+Inputs!$D$66,Inputs!$D$66>0),Inputs!$D$29*Inputs!$C$15/Inputs!$D$66,0) -> 0
B21: Project management | C21: =SUM(H21:BO21) -> 0 | H21: =-IF(AND(H$44>Inputs!$D$65,H$44<=Inputs!$D$65+Inputs!$D$66,Inputs!$D$66>0),(Inputs!$D$28+Inputs!$D$29)*Inputs!$C$15*Inputs!$E$30/Inputs!$D$66,0) -> 0 | I21: =-IF(AND(I$44>Inputs!$D$65,I$44<=Inputs!$D$65+Inputs!$D$66,Inputs!$D$66>0),(Inputs!$D$28+Inputs!$D$29)*Inputs!$C$15*Inputs!$E$30/Inputs!$D$66,0) -> 0 | J21: =-IF(AND(J$44>Inputs!$D$65,J$44<=Inputs!$D$65+Inputs!$D$66,Inputs!$D$66>0),(Inputs!$D$28+Inputs!$D$29)*Inputs!$C$15*Inputs!$E$30/Inputs!$D$66,0) -> 0 | K21: =-IF(AND(K$44>Inputs!$D$65,K$44<=Inputs!$D$65+Inputs!$D$66,Inputs!$D$66>0),(Inputs!$D$28+Inputs!$D$29)*Inputs!$C$15*Inputs!$E$30/Inputs!$D$66,0) -> 0 | L21: =-IF(AND(L$44>Inputs!$D$65,L$44<=Inputs!$D$65+Inputs!$D$66,Inputs!$D$66>0),(Inputs!$D$28+Inputs!$D$29)*Inputs!$C$15*Inputs!$E$30/Inputs!$D$66,0) -> 0 | M21: =-IF(AND(M$44>Inputs!$D$65,M$44<=Inputs!$D$65+Inputs!$D$66,Inputs!$D$66>0),(Inputs!$D$28+Inputs!$D$29)*Inputs!$C$15*Inputs!$E$30/Inputs!$D$66,0) -> 0 | N21: =-IF(AND(N$44>Inputs!$D$65,N$44<=Inputs!$D$65+Inputs!$D$66,Inputs!$D$66>0),(Inputs!$D$28+Inputs!$D$29)*Inputs!$C$15*Inputs!$E$30/Inputs!$D$66,0) -> 0 | O21: =-IF(AND(O$44>Inputs!$D$65,O$44<=Inputs!$D$65+Inputs!$D$66,Inputs!$D$66>0),(Inputs!$D$28+Inputs!$D$29)*Inputs!$C$15*Inputs!$E$30/Inputs!$D$66,0) -> 0 | ... BO21: =-IF(AND(BO$44>Inputs!$D$65,BO$44<=Inputs!$D$65+Inputs!$D$66,Inputs!$D$66>0),(Inputs!$D$28+Inputs!$D$29)*Inputs!$C$15*Inputs!$E$30/Inputs!$D$66,0) -> 0
B22: Other costs | C22: =SUM(H22:BO22) -> 0 | H22: =-H50 -> 0 | I22: =-I50 -> 0 | J22: =-J50 -> 0 | K22: =-K50 -> 0 | L22: =-L50 -> 0 | M22: =-M50 -> 0 | N22: =-N50 -> 0 | O22: =-O50 -> 0 | ... BO22: =-BO50 -> 0
B23: Total project costs | C23: =SUM(H23:BO23) -> 0 | H23: =SUM(H18:H22) -> 0 | I23: =SUM(I18:I22) -> 0 | J23: =SUM(J18:J22) -> 0 | K23: =SUM(K18:K22) -> 0 | L23: =SUM(L18:L22) -> 0 | M23: =SUM(M18:M22) -> 0 | N23: =SUM(N18:N22) -> 0 | O23: =SUM(O18:O22) -> 0 | ... BO23: =SUM(BO18:BO22) -> 0
B25: Gross margin | C25: =SUM(H25:BO25) -> 0 | H25: =H16+H23 -> 0 | I25: =I16+I23 -> 0 | J25: =J16+J23 -> 0 | K25: =K16+K23 -> 0 | L25: =L16+L23 -> 0 | M25: =M16+M23 -> 0 | N25: =N16+N23 -> 0 | O25: =O16+O23 -> 0 | ... BO25: =BO16+BO23 -> 0
B27: PIK interest expense | C27: =SUM(H27:BO27) -> #REF! | H27: =-H74 -> 0 | I27: =-I74 -> #REF! | J27: =-J74 -> #REF! | K27: =-K74 -> #REF! | L27: =-L74 -> #REF! | M27: =-M74 -> #REF! | N27: =-N74 -> #REF! | O27: =-O74 -> #REF! | ... BO27: =-BO74 -> #REF!
B28: Opening fee | C28: =SUM(H28:BO28) -> 0 | H28: =-IF(H$44=1,H72,0) -> 0 | I28: =-IF(I$44=1,I72,0) -> 0 | J28: =-IF(J$44=1,J72,0) -> 0 | K28: =-IF(K$44=1,K72,0) -> 0 | L28: =-IF(L$44=1,L72,0) -> 0 | M28: =-IF(M$44=1,M72,0) -> 0 | N28: =-IF(N$44=1,N72,0) -> 0 | O28: =-IF(O$44=1,O72,0) -> 0 | ... BO28: =-IF(BO$44=1,BO72,0) -> 0
B30: Profit before tax (EBT) | C30: =SUM(H30:BO30) -> #REF! | H30: =H25+H27+H28 -> 0 | I30: =I25+I27+I28 -> #REF! | J30: =J25+J27+J28 -> #REF! | K30: =K25+K27+K28 -> #REF! | L30: =L25+L27+L28 -> #REF! | M30: =M25+M27+M28 -> #REF! | N30: =N25+N27+N28 -> #REF! | O30: =O25+O27+O28 -> #REF! | ... BO30: =BO25+BO27+BO28 -> #REF!
B32: CASH FLOW (MONTHLY)
B33: OPERATING CASH FLOW
B34: Cash in from sales | C34: =SUM(H34:BO34) -> 0 | H34: =H55 -> 0 | I34: =I55 -> 0 | J34: =J55 -> 0 | K34: =K55 -> 0 | L34: =L55 -> 0 | M34: =M55 -> 0 | N34: =N55 -> 0 | O34: =O55 -> 0 | ... BO34: =BO55 -> 0
B35: of which: reservation | C35: =SUM(H35:BO35) -> 0 | H35: =IF(AND(H$44>Inputs!$D$65+Inputs!$D$67,H$44<=Inputs!$D$65+Inputs!$D$67+1,Inputs!$D$66>Inputs!$D$67),Inputs!$C$18*Inputs!$D$74,0) -> 0 | I35: =IF(AND(I$44>Inputs!$D$65+Inputs!$D$67,I$44<=Inputs!$D$65+Inputs!$D$67+1,Inputs!$D$66>Inputs!$D$67),Inputs!$C$18*Inputs!$D$74,0) -> 0 | J35: =IF(AND(J$44>Inputs!$D$65+Inputs!$D$67,J$44<=Inputs!$D$65+Inputs!$D$67+1,Inputs!$D$66>Inputs!$D$67),Inputs!$C$18*Inputs!$D$74,0) -> 0 | K35: =IF(AND(K$44>Inputs!$D$65+Inputs!$D$67,K$44<=Inputs!$D$65+Inputs!$D$67+1,Inputs!$D$66>Inputs!$D$67),Inputs!$C$18*Inputs!$D$74,0) -> 0 | L35: =IF(AND(L$44>Inputs!$D$65+Inputs!$D$67,L$44<=Inputs!$D$65+Inputs!$D$67+1,Inputs!$D$66>Inputs!$D$67),Inputs!$C$18*Inputs!$D$74,0) -> 0 | M35: =IF(AND(M$44>Inputs!$D$65+Inputs!$D$67,M$44<=Inputs!$D$65+Inputs!$D$67+1,Inputs!$D$66>Inputs!$D$67),Inputs!$C$18*Inputs!$D$74,0) -> 0 | N35: =IF(AND(N$44>Inputs!$D$65+Inputs!$D$67,N$44<=Inputs!$D$65+Inputs!$D$67+1,Inputs!$D$66>Inputs!$D$67),Inputs!$C$18*Inputs!$D$74,0) -> 0 | O35: =IF(AND(O$44>Inputs!$D$65+Inputs!$D$67,O$44<=Inputs!$D$65+Inputs!$D$67+1,Inputs!$D$66>Inputs!$D$67),Inputs!$C$18*Inputs!$D$74,0) -> 0 | ... BO35: =IF(AND(BO$44>Inputs!$D$65+Inputs!$D$67,BO$44<=Inputs!$D$65+Inputs!$D$67+1,Inputs!$D$66>Inputs!$D$67),Inputs!$C$18*Inputs!$D$74,0) -> 0
B36: of which: progress payments | C36: =SUM(H36:BO36) -> 0 | H36: =IF(AND(H$44>Inputs!$D$65+Inputs!$D$67,H$44<=Inputs!$D$65+Inputs!$D$66,Inputs!$D$66>Inputs!$D$67),Inputs!$C$18*Inputs!$D$75/MAX(Inputs!$D$66-Inputs!$D$67,1),0) -> 0 | I36: =IF(AND(I$44>Inputs!$D$65+Inputs!$D$67,I$44<=Inputs!$D$65+Inputs!$D$66,Inputs!$D$66>Inputs!$D$67),Inputs!$C$18*Inputs!$D$75/MAX(Inputs!$D$66-Inputs!$D$67,1),0) -> 0 | J36: =IF(AND(J$44>Inputs!$D$65+Inputs!$D$67,J$44<=Inputs!$D$65+Inputs!$D$66,Inputs!$D$66>Inputs!$D$67),Inputs!$C$18*Inputs!$D$75/MAX(Inputs!$D$66-Inputs!$D$67,1),0) -> 0 | K36: =IF(AND(K$44>Inputs!$D$65+Inputs!$D$67,K$44<=Inputs!$D$65+Inputs!$D$66,Inputs!$D$66>Inputs!$D$67),Inputs!$C$18*Inputs!$D$75/MAX(Inputs!$D$66-Inputs!$D$67,1),0) -> 0 | L36: =IF(AND(L$44>Inputs!$D$65+Inputs!$D$67,L$44<=Inputs!$D$65+Inputs!$D$66,Inputs!$D$66>Inputs!$D$67),Inputs!$C$18*Inputs!$D$75/MAX(Inputs!$D$66-Inputs!$D$67,1),0) -> 0 | M36: =IF(AND(M$44>Inputs!$D$65+Inputs!$D$67,M$44<=Inputs!$D$65+Inputs!$D$66,Inputs!$D$66>Inputs!$D$67),Inputs!$C$18*Inputs!$D$75/MAX(Inputs!$D$66-Inputs!$D$67,1),0) -> 0 | N36: =IF(AND(N$44>Inputs!$D$65+Inputs!$D$67,N$44<=Inputs!$D$65+Inputs!$D$66,Inputs!$D$66>Inputs!$D$67),Inputs!$C$18*Inputs!$D$75/MAX(Inputs!$D$66-Inputs!$D$67,1),0) -> 0 | O36: =IF(AND(O$44>Inputs!$D$65+Inputs!$D$67,O$44<=Inputs!$D$65+Inputs!$D$66,Inputs!$D$66>Inputs!$D$67),Inputs!$C$18*Inputs!$D$75/MAX(Inputs!$D$66-Inputs!$D$67,1),0) -> 0 | ... BO36: =IF(AND(BO$44>Inputs!$D$65+Inputs!$D$67,BO$44<=Inputs!$D$65+Inputs!$D$66,Inputs!$D$66>Inputs!$D$67),Inputs!$C$18*Inputs!$D$75/MAX(Inputs!$D$66-Inputs!$D$67,1),0) -> 0
B37: of which: delivery | C37: =SUM(H37:BO37) -> 0 | H37: =IF(H$44=Inputs!$D$65+Inputs!$D$66+Inputs!$D$77,Inputs!$C$18*Inputs!$D$76,0) -> 0 | I37: =IF(I$44=Inputs!$D$65+Inputs!$D$66+Inputs!$D$77,Inputs!$C$18*Inputs!$D$76,0) -> 0 | J37: =IF(J$44=Inputs!$D$65+Inputs!$D$66+Inputs!$D$77,Inputs!$C$18*Inputs!$D$76,0) -> 0 | K37: =IF(K$44=Inputs!$D$65+Inputs!$D$66+Inputs!$D$77,Inputs!$C$18*Inputs!$D$76,0) -> 0 | L37: =IF(L$44=Inputs!$D$65+Inputs!$D$66+Inputs!$D$77,Inputs!$C$18*Inputs!$D$76,0) -> 0 | M37: =IF(M$44=Inputs!$D$65+Inputs!$D$66+Inputs!$D$77,Inputs!$C$18*Inputs!$D$76,0) -> 0 | N37: =IF(N$44=Inputs!$D$65+Inputs!$D$66+Inputs!$D$77,Inputs!$C$18*Inputs!$D$76,0) -> 0 | O37: =IF(O$44=Inputs!$D$65+Inputs!$D$66+Inputs!$D$77,Inputs!$C$18*Inputs!$D$76,0) -> 0 | ... BO37: =IF(BO$44=Inputs!$D$65+Inputs!$D$66+Inputs!$D$77,Inputs!$C$18*Inputs!$D$76,0) -> 0
B38: Total Operating Cash Flow | C38: =SUM(H38:BO38) -> 0 | H38: =H34 -> 0 | I38: =I34 -> 0 | J38: =J34 -> 0 | K38: =K34 -> 0 | L38: =L34 -> 0 | M38: =M34 -> 0 | N38: =N34 -> 0 | O38: =O34 -> 0 | ... BO38: =BO34 -> 0
B39: INVESTING CASH FLOW
B40: Acquisition (capex) | C40: =SUM(H40:BO40) -> 0 | H40: =-H48 -> 0 | I40: =-I48 -> 0 | J40: =-J48 -> 0 | K40: =-K48 -> 0 | L40: =-L48 -> 0 | M40: =-M48 -> 0 | N40: =-N48 -> 0 | O40: =-O48 -> 0 | ... BO40: =-BO48 -> 0
B41: Construction (capex) | C41: =SUM(H41:BO41) -> 0 | H41: =-(H49+H50) -> 0 | I41: =-(I49+I50) -> 0 | J41: =-(J49+J50) -> 0 | K41: =-(K49+K50) -> 0 | L41: =-(L49+L50) -> 0 | M41: =-(M49+M50) -> 0 | N41: =-(N49+N50) -> 0 | O41: =-(O49+O50) -> 0 | ... BO41: =-(BO49+BO50) -> 0
B42: Total Investing Cash Flow | C42: =SUM(H42:BO42) -> 0 | H42: =SUM(H40:H41) -> 0 | I42: =SUM(I40:I41) -> 0 | J42: =SUM(J40:J41) -> 0 | K42: =SUM(K40:K41) -> 0 | L42: =SUM(L40:L41) -> 0 | M42: =SUM(M40:M41) -> 0 | N42: =SUM(N40:N41) -> 0 | O42: =SUM(O40:O41) -> 0 | ... BO42: =SUM(BO40:BO41) -> 0
B44: Line | C44: Total | H44: 1 | I44: 2 | J44: 3 | K44: 4 | L44: 5 | M44: 6 | N44: 7 | O44: 8 | P44: 9 | Q44: 10 | R44: 11 | S44: 12 | T44: 13 | U44: 14 | V44: 15 | W44: 16 | X44: 17 | Y44: 18 | Z44: 19 | AA44: 20 | AB44: 21 | AC44: 22 | AD44: 23 | AE44: 24 | AF44: 25 | AG44: 26 | AH44: 27 | AI44: 28 | AJ44: 29 | AK44: 30 | AL44: 31 | AM44: 32 | AN44: 33 | AO44: 34 | AP44: 35 | AQ44: 36 | AR44: 37 | AS44: 38 | AT44: 39 | AU44: 40 | AV44: 41 | AW44: 42 | AX44: 43 | AY44: 44 | AZ44: 45 | BA44: 46 | BB44: 47 | BC44: 48 | BD44: 49 | BE44: 50 | BF44: 51 | BG44: 52 | BH44: 53 | BI44: 54 | BJ44: 55 | BK44: 56 | BL44: 57 | BM44: 58 | BN44: 59 | BO44: 60
H45: =+EOMONTH(TODAY(),0) -> 46142 | I45: =+EOMONTH(H45,1) -> 46173 | J45: =+EOMONTH(I45,1) -> 46203 | K45: =+EOMONTH(J45,1) -> 46234 | L45: =+EOMONTH(K45,1) -> 46265 | M45: =+EOMONTH(L45,1) -> 46295 | N45: =+EOMONTH(M45,1) -> 46326 | O45: =+EOMONTH(N45,1) -> 46356 | P45: =+EOMONTH(O45,1) -> 46387 | ... BO45: =+EOMONTH(BN45,1) -> 47938
B46: PROJECT COSTS
B48: Acquisition + Related (cost) | C48: =SUM(H48:BO48) -> 0 | H48: =IF(1=1,Inputs!$D$23*(1+Inputs!$D$24),0) -> 0 | I48: =IF(2=1,Inputs!$D$23*(1+Inputs!$D$24),0) -> 0 | J48: =IF(3=1,Inputs!$D$23*(1+Inputs!$D$24),0) -> 0 | K48: =IF(4=1,Inputs!$D$23*(1+Inputs!$D$24),0) -> 0 | L48: =IF(5=1,Inputs!$D$23*(1+Inputs!$D$24),0) -> 0 | M48: =IF(6=1,Inputs!$D$23*(1+Inputs!$D$24),0) -> 0 | N48: =IF(7=1,Inputs!$D$23*(1+Inputs!$D$24),0) -> 0 | O48: =IF(8=1,Inputs!$D$23*(1+Inputs!$D$24),0) -> 0 | P48: =IF(9=1,Inputs!$D$23*(1+Inputs!$D$24),0) -> 0 | Q48: =IF(10=1,Inputs!$D$23*(1+Inputs!$D$24),0) -> 0 | R48: =IF(11=1,Inputs!$D$23*(1+Inputs!$D$24),0) -> 0 | S48: =IF(12=1,Inputs!$D$23*(1+Inputs!$D$24),0) -> 0 | T48: =IF(13=1,Inputs!$D$23*(1+Inputs!$D$24),0) -> 0 | U48: =IF(14=1,Inputs!$D$23*(1+Inputs!$D$24),0) -> 0 | V48: =IF(15=1,Inputs!$D$23*(1+Inputs!$D$24),0) -> 0 | W48: =IF(16=1,Inputs!$D$23*(1+Inputs!$D$24),0) -> 0 | X48: =IF(17=1,Inputs!$D$23*(1+Inputs!$D$24),0) -> 0 | Y48: =IF(18=1,Inputs!$D$23*(1+Inputs!$D$24),0) -> 0 | Z48: =IF(19=1,Inputs!$D$23*(1+Inputs!$D$24),0) -> 0 | AA48: =IF(20=1,Inputs!$D$23*(1+Inputs!$D$24),0) -> 0 | AB48: =IF(21=1,Inputs!$D$23*(1+Inputs!$D$24),0) -> 0 | AC48: =IF(22=1,Inputs!$D$23*(1+Inputs!$D$24),0) -> 0 | AD48: =IF(23=1,Inputs!$D$23*(1+Inputs!$D$24),0) -> 0 | AE48: =IF(24=1,Inputs!$D$23*(1+Inputs!$D$24),0) -> 0 | AF48: =IF(25=1,Inputs!$D$23*(1+Inputs!$D$24),0) -> 0 | AG48: =IF(26=1,Inputs!$D$23*(1+Inputs!$D$24),0) -> 0 | AH48: =IF(27=1,Inputs!$D$23*(1+Inputs!$D$24),0) -> 0 | AI48: =IF(28=1,Inputs!$D$23*(1+Inputs!$D$24),0) -> 0 | AJ48: =IF(29=1,Inputs!$D$23*(1+Inputs!$D$24),0) -> 0 | AK48: =IF(30=1,Inputs!$D$23*(1+Inputs!$D$24),0) -> 0 | AL48: =IF(31=1,Inputs!$D$23*(1+Inputs!$D$24),0) -> 0 | AM48: =IF(32=1,Inputs!$D$23*(1+Inputs!$D$24),0) -> 0 | AN48: =IF(33=1,Inputs!$D$23*(1+Inputs!$D$24),0) -> 0 | AO48: =IF(34=1,Inputs!$D$23*(1+Inputs!$D$24),0) -> 0 | AP48: =IF(35=1,Inputs!$D$23*(1+Inputs!$D$24),0) -> 0 | AQ48: =IF(36=1,Inputs!$D$23*(1+Inputs!$D$24),0) -> 0 | AR48: =IF(37=1,Inputs!$D$23*(1+Inputs!$D$24),0) -> 0 | AS48: =IF(38=1,Inputs!$D$23*(1+Inputs!$D$24),0) -> 0 | AT48: =IF(39=1,Inputs!$D$23*(1+Inputs!$D$24),0) -> 0 | AU48: =IF(40=1,Inputs!$D$23*(1+Inputs!$D$24),0) -> 0 | AV48: =IF(41=1,Inputs!$D$23*(1+Inputs!$D$24),0) -> 0 | AW48: =IF(42=1,Inputs!$D$23*(1+Inputs!$D$24),0) -> 0 | AX48: =IF(43=1,Inputs!$D$23*(1+Inputs!$D$24),0) -> 0 | AY48: =IF(44=1,Inputs!$D$23*(1+Inputs!$D$24),0) -> 0 | AZ48: =IF(45=1,Inputs!$D$23*(1+Inputs!$D$24),0) -> 0 | BA48: =IF(46=1,Inputs!$D$23*(1+Inputs!$D$24),0) -> 0 | BB48: =IF(47=1,Inputs!$D$23*(1+Inputs!$D$24),0) -> 0 | BC48: =IF(48=1,Inputs!$D$23*(1+Inputs!$D$24),0) -> 0 | BD48: =IF(49=1,Inputs!$D$23*(1+Inputs!$D$24),0) -> 0 | BE48: =IF(50=1,Inputs!$D$23*(1+Inputs!$D$24),0) -> 0 | BF48: =IF(51=1,Inputs!$D$23*(1+Inputs!$D$24),0) -> 0 | BG48: =IF(52=1,Inputs!$D$23*(1+Inputs!$D$24),0) -> 0 | BH48: =IF(53=1,Inputs!$D$23*(1+Inputs!$D$24),0) -> 0 | BI48: =IF(54=1,Inputs!$D$23*(1+Inputs!$D$24),0) -> 0 | BJ48: =IF(55=1,Inputs!$D$23*(1+Inputs!$D$24),0) -> 0 | BK48: =IF(56=1,Inputs!$D$23*(1+Inputs!$D$24),0) -> 0 | BL48: =IF(57=1,Inputs!$D$23*(1+Inputs!$D$24),0) -> 0 | BM48: =IF(58=1,Inputs!$D$23*(1+Inputs!$D$24),0) -> 0 | BN48: =IF(59=1,Inputs!$D$23*(1+Inputs!$D$24),0) -> 0 | BO48: =IF(60=1,Inputs!$D$23*(1+Inputs!$D$24),0) -> 0
B49: Construction (cost) | C49: =SUM(H49:BO49) -> 0 | H49: =IF(AND(1>Inputs!$D$65,1<=Inputs!$D$65+Inputs!$D$66,Inputs!$D$66>0),(Inputs!$D$28*Inputs!$C$15+Inputs!$D$29*Inputs!$C$15)*(1+Inputs!$D$30)/Inputs!$D$66,0) -> 0 | I49: =IF(AND(2>Inputs!$D$65,2<=Inputs!$D$65+Inputs!$D$66,Inputs!$D$66>0),(Inputs!$D$28*Inputs!$C$15+Inputs!$D$29*Inputs!$C$15)*(1+Inputs!$D$30)/Inputs!$D$66,0) -> 0 | J49: =IF(AND(3>Inputs!$D$65,3<=Inputs!$D$65+Inputs!$D$66,Inputs!$D$66>0),(Inputs!$D$28*Inputs!$C$15+Inputs!$D$29*Inputs!$C$15)*(1+Inputs!$D$30)/Inputs!$D$66,0) -> 0 | K49: =IF(AND(4>Inputs!$D$65,4<=Inputs!$D$65+Inputs!$D$66,Inputs!$D$66>0),(Inputs!$D$28*Inputs!$C$15+Inputs!$D$29*Inputs!$C$15)*(1+Inputs!$D$30)/Inputs!$D$66,0) -> 0 | L49: =IF(AND(5>Inputs!$D$65,5<=Inputs!$D$65+Inputs!$D$66,Inputs!$D$66>0),(Inputs!$D$28*Inputs!$C$15+Inputs!$D$29*Inputs!$C$15)*(1+Inputs!$D$30)/Inputs!$D$66,0) -> 0 | M49: =IF(AND(6>Inputs!$D$65,6<=Inputs!$D$65+Inputs!$D$66,Inputs!$D$66>0),(Inputs!$D$28*Inputs!$C$15+Inputs!$D$29*Inputs!$C$15)*(1+Inputs!$D$30)/Inputs!$D$66,0) -> 0 | N49: =IF(AND(7>Inputs!$D$65,7<=Inputs!$D$65+Inputs!$D$66,Inputs!$D$66>0),(Inputs!$D$28*Inputs!$C$15+Inputs!$D$29*Inputs!$C$15)*(1+Inputs!$D$30)/Inputs!$D$66,0) -> 0 | O49: =IF(AND(8>Inputs!$D$65,8<=Inputs!$D$65+Inputs!$D$66,Inputs!$D$66>0),(Inputs!$D$28*Inputs!$C$15+Inputs!$D$29*Inputs!$C$15)*(1+Inputs!$D$30)/Inputs!$D$66,0) -> 0 | P49: =IF(AND(9>Inputs!$D$65,9<=Inputs!$D$65+Inputs!$D$66,Inputs!$D$66>0),(Inputs!$D$28*Inputs!$C$15+Inputs!$D$29*Inputs!$C$15)*(1+Inputs!$D$30)/Inputs!$D$66,0) -> 0 | Q49: =IF(AND(10>Inputs!$D$65,10<=Inputs!$D$65+Inputs!$D$66,Inputs!$D$66>0),(Inputs!$D$28*Inputs!$C$15+Inputs!$D$29*Inputs!$C$15)*(1+Inputs!$D$30)/Inputs!$D$66,0) -> 0 | R49: =IF(AND(11>Inputs!$D$65,11<=Inputs!$D$65+Inputs!$D$66,Inputs!$D$66>0),(Inputs!$D$28*Inputs!$C$15+Inputs!$D$29*Inputs!$C$15)*(1+Inputs!$D$30)/Inputs!$D$66,0) -> 0 | S49: =IF(AND(12>Inputs!$D$65,12<=Inputs!$D$65+Inputs!$D$66,Inputs!$D$66>0),(Inputs!$D$28*Inputs!$C$15+Inputs!$D$29*Inputs!$C$15)*(1+Inputs!$D$30)/Inputs!$D$66,0) -> 0 | T49: =IF(AND(13>Inputs!$D$65,13<=Inputs!$D$65+Inputs!$D$66,Inputs!$D$66>0),(Inputs!$D$28*Inputs!$C$15+Inputs!$D$29*Inputs!$C$15)*(1+Inputs!$D$30)/Inputs!$D$66,0) -> 0 | U49: =IF(AND(14>Inputs!$D$65,14<=Inputs!$D$65+Inputs!$D$66,Inputs!$D$66>0),(Inputs!$D$28*Inputs!$C$15+Inputs!$D$29*Inputs!$C$15)*(1+Inputs!$D$30)/Inputs!$D$66,0) -> 0 | V49: =IF(AND(15>Inputs!$D$65,15<=Inputs!$D$65+Inputs!$D$66,Inputs!$D$66>0),(Inputs!$D$28*Inputs!$C$15+Inputs!$D$29*Inputs!$C$15)*(1+Inputs!$D$30)/Inputs!$D$66,0) -> 0 | W49: =IF(AND(16>Inputs!$D$65,16<=Inputs!$D$65+Inputs!$D$66,Inputs!$D$66>0),(Inputs!$D$28*Inputs!$C$15+Inputs!$D$29*Inputs!$C$15)*(1+Inputs!$D$30)/Inputs!$D$66,0) -> 0 | X49: =IF(AND(17>Inputs!$D$65,17<=Inputs!$D$65+Inputs!$D$66,Inputs!$D$66>0),(Inputs!$D$28*Inputs!$C$15+Inputs!$D$29*Inputs!$C$15)*(1+Inputs!$D$30)/Inputs!$D$66,0) -> 0 | Y49: =IF(AND(18>Inputs!$D$65,18<=Inputs!$D$65+Inputs!$D$66,Inputs!$D$66>0),(Inputs!$D$28*Inputs!$C$15+Inputs!$D$29*Inputs!$C$15)*(1+Inputs!$D$30)/Inputs!$D$66,0) -> 0 | Z49: =IF(AND(19>Inputs!$D$65,19<=Inputs!$D$65+Inputs!$D$66,Inputs!$D$66>0),(Inputs!$D$28*Inputs!$C$15+Inputs!$D$29*Inputs!$C$15)*(1+Inputs!$D$30)/Inputs!$D$66,0) -> 0 | AA49: =IF(AND(20>Inputs!$D$65,20<=Inputs!$D$65+Inputs!$D$66,Inputs!$D$66>0),(Inputs!$D$28*Inputs!$C$15+Inputs!$D$29*Inputs!$C$15)*(1+Inputs!$D$30)/Inputs!$D$66,0) -> 0 | AB49: =IF(AND(21>Inputs!$D$65,21<=Inputs!$D$65+Inputs!$D$66,Inputs!$D$66>0),(Inputs!$D$28*Inputs!$C$15+Inputs!$D$29*Inputs!$C$15)*(1+Inputs!$D$30)/Inputs!$D$66,0) -> 0 | AC49: =IF(AND(22>Inputs!$D$65,22<=Inputs!$D$65+Inputs!$D$66,Inputs!$D$66>0),(Inputs!$D$28*Inputs!$C$15+Inputs!$D$29*Inputs!$C$15)*(1+Inputs!$D$30)/Inputs!$D$66,0) -> 0 | AD49: =IF(AND(23>Inputs!$D$65,23<=Inputs!$D$65+Inputs!$D$66,Inputs!$D$66>0),(Inputs!$D$28*Inputs!$C$15+Inputs!$D$29*Inputs!$C$15)*(1+Inputs!$D$30)/Inputs!$D$66,0) -> 0 | AE49: =IF(AND(24>Inputs!$D$65,24<=Inputs!$D$65+Inputs!$D$66,Inputs!$D$66>0),(Inputs!$D$28*Inputs!$C$15+Inputs!$D$29*Inputs!$C$15)*(1+Inputs!$D$30)/Inputs!$D$66,0) -> 0 | AF49: =IF(AND(25>Inputs!$D$65,25<=Inputs!$D$65+Inputs!$D$66,Inputs!$D$66>0),(Inputs!$D$28*Inputs!$C$15+Inputs!$D$29*Inputs!$C$15)*(1+Inputs!$D$30)/Inputs!$D$66,0) -> 0 | AG49: =IF(AND(26>Inputs!$D$65,26<=Inputs!$D$65+Inputs!$D$66,Inputs!$D$66>0),(Inputs!$D$28*Inputs!$C$15+Inputs!$D$29*Inputs!$C$15)*(1+Inputs!$D$30)/Inputs!$D$66,0) -> 0 | AH49: =IF(AND(27>Inputs!$D$65,27<=Inputs!$D$65+Inputs!$D$66,Inputs!$D$66>0),(Inputs!$D$28*Inputs!$C$15+Inputs!$D$29*Inputs!$C$15)*(1+Inputs!$D$30)/Inputs!$D$66,0) -> 0 | AI49: =IF(AND(28>Inputs!$D$65,28<=Inputs!$D$65+Inputs!$D$66,Inputs!$D$66>0),(Inputs!$D$28*Inputs!$C$15+Inputs!$D$29*Inputs!$C$15)*(1+Inputs!$D$30)/Inputs!$D$66,0) -> 0 | AJ49: =IF(AND(29>Inputs!$D$65,29<=Inputs!$D$65+Inputs!$D$66,Inputs!$D$66>0),(Inputs!$D$28*Inputs!$C$15+Inputs!$D$29*Inputs!$C$15)*(1+Inputs!$D$30)/Inputs!$D$66,0) -> 0 | AK49: =IF(AND(30>Inputs!$D$65,30<=Inputs!$D$65+Inputs!$D$66,Inputs!$D$66>0),(Inputs!$D$28*Inputs!$C$15+Inputs!$D$29*Inputs!$C$15)*(1+Inputs!$D$30)/Inputs!$D$66,0) -> 0 | AL49: =IF(AND(31>Inputs!$D$65,31<=Inputs!$D$65+Inputs!$D$66,Inputs!$D$66>0),(Inputs!$D$28*Inputs!$C$15+Inputs!$D$29*Inputs!$C$15)*(1+Inputs!$D$30)/Inputs!$D$66,0) -> 0 | AM49: =IF(AND(32>Inputs!$D$65,32<=Inputs!$D$65+Inputs!$D$66,Inputs!$D$66>0),(Inputs!$D$28*Inputs!$C$15+Inputs!$D$29*Inputs!$C$15)*(1+Inputs!$D$30)/Inputs!$D$66,0) -> 0 | AN49: =IF(AND(33>Inputs!$D$65,33<=Inputs!$D$65+Inputs!$D$66,Inputs!$D$66>0),(Inputs!$D$28*Inputs!$C$15+Inputs!$D$29*Inputs!$C$15)*(1+Inputs!$D$30)/Inputs!$D$66,0) -> 0 | AO49: =IF(AND(34>Inputs!$D$65,34<=Inputs!$D$65+Inputs!$D$66,Inputs!$D$66>0),(Inputs!$D$28*Inputs!$C$15+Inputs!$D$29*Inputs!$C$15)*(1+Inputs!$D$30)/Inputs!$D$66,0) -> 0 | AP49: =IF(AND(35>Inputs!$D$65,35<=Inputs!$D$65+Inputs!$D$66,Inputs!$D$66>0),(Inputs!$D$28*Inputs!$C$15+Inputs!$D$29*Inputs!$C$15)*(1+Inputs!$D$30)/Inputs!$D$66,0) -> 0 | AQ49: =IF(AND(36>Inputs!$D$65,36<=Inputs!$D$65+Inputs!$D$66,Inputs!$D$66>0),(Inputs!$D$28*Inputs!$C$15+Inputs!$D$29*Inputs!$C$15)*(1+Inputs!$D$30)/Inputs!$D$66,0) -> 0 | AR49: =IF(AND(37>Inputs!$D$65,37<=Inputs!$D$65+Inputs!$D$66,Inputs!$D$66>0),(Inputs!$D$28*Inputs!$C$15+Inputs!$D$29*Inputs!$C$15)*(1+Inputs!$D$30)/Inputs!$D$66,0) -> 0 | AS49: =IF(AND(38>Inputs!$D$65,38<=Inputs!$D$65+Inputs!$D$66,Inputs!$D$66>0),(Inputs!$D$28*Inputs!$C$15+Inputs!$D$29*Inputs!$C$15)*(1+Inputs!$D$30)/Inputs!$D$66,0) -> 0 | AT49: =IF(AND(39>Inputs!$D$65,39<=Inputs!$D$65+Inputs!$D$66,Inputs!$D$66>0),(Inputs!$D$28*Inputs!$C$15+Inputs!$D$29*Inputs!$C$15)*(1+Inputs!$D$30)/Inputs!$D$66,0) -> 0 | AU49: =IF(AND(40>Inputs!$D$65,40<=Inputs!$D$65+Inputs!$D$66,Inputs!$D$66>0),(Inputs!$D$28*Inputs!$C$15+Inputs!$D$29*Inputs!$C$15)*(1+Inputs!$D$30)/Inputs!$D$66,0) -> 0 | AV49: =IF(AND(41>Inputs!$D$65,41<=Inputs!$D$65+Inputs!$D$66,Inputs!$D$66>0),(Inputs!$D$28*Inputs!$C$15+Inputs!$D$29*Inputs!$C$15)*(1+Inputs!$D$30)/Inputs!$D$66,0) -> 0 | AW49: =IF(AND(42>Inputs!$D$65,42<=Inputs!$D$65+Inputs!$D$66,Inputs!$D$66>0),(Inputs!$D$28*Inputs!$C$15+Inputs!$D$29*Inputs!$C$15)*(1+Inputs!$D$30)/Inputs!$D$66,0) -> 0 | AX49: =IF(AND(43>Inputs!$D$65,43<=Inputs!$D$65+Inputs!$D$66,Inputs!$D$66>0),(Inputs!$D$28*Inputs!$C$15+Inputs!$D$29*Inputs!$C$15)*(1+Inputs!$D$30)/Inputs!$D$66,0) -> 0 | AY49: =IF(AND(44>Inputs!$D$65,44<=Inputs!$D$65+Inputs!$D$66,Inputs!$D$66>0),(Inputs!$D$28*Inputs!$C$15+Inputs!$D$29*Inputs!$C$15)*(1+Inputs!$D$30)/Inputs!$D$66,0) -> 0 | AZ49: =IF(AND(45>Inputs!$D$65,45<=Inputs!$D$65+Inputs!$D$66,Inputs!$D$66>0),(Inputs!$D$28*Inputs!$C$15+Inputs!$D$29*Inputs!$C$15)*(1+Inputs!$D$30)/Inputs!$D$66,0) -> 0 | BA49: =IF(AND(46>Inputs!$D$65,46<=Inputs!$D$65+Inputs!$D$66,Inputs!$D$66>0),(Inputs!$D$28*Inputs!$C$15+Inputs!$D$29*Inputs!$C$15)*(1+Inputs!$D$30)/Inputs!$D$66,0) -> 0 | BB49: =IF(AND(47>Inputs!$D$65,47<=Inputs!$D$65+Inputs!$D$66,Inputs!$D$66>0),(Inputs!$D$28*Inputs!$C$15+Inputs!$D$29*Inputs!$C$15)*(1+Inputs!$D$30)/Inputs!$D$66,0) -> 0 | BC49: =IF(AND(48>Inputs!$D$65,48<=Inputs!$D$65+Inputs!$D$66,Inputs!$D$66>0),(Inputs!$D$28*Inputs!$C$15+Inputs!$D$29*Inputs!$C$15)*(1+Inputs!$D$30)/Inputs!$D$66,0) -> 0 | BD49: =IF(AND(49>Inputs!$D$65,49<=Inputs!$D$65+Inputs!$D$66,Inputs!$D$66>0),(Inputs!$D$28*Inputs!$C$15+Inputs!$D$29*Inputs!$C$15)*(1+Inputs!$D$30)/Inputs!$D$66,0) -> 0 | BE49: =IF(AND(50>Inputs!$D$65,50<=Inputs!$D$65+Inputs!$D$66,Inputs!$D$66>0),(Inputs!$D$28*Inputs!$C$15+Inputs!$D$29*Inputs!$C$15)*(1+Inputs!$D$30)/Inputs!$D$66,0) -> 0 | BF49: =IF(AND(51>Inputs!$D$65,51<=Inputs!$D$65+Inputs!$D$66,Inputs!$D$66>0),(Inputs!$D$28*Inputs!$C$15+Inputs!$D$29*Inputs!$C$15)*(1+Inputs!$D$30)/Inputs!$D$66,0) -> 0 | BG49: =IF(AND(52>Inputs!$D$65,52<=Inputs!$D$65+Inputs!$D$66,Inputs!$D$66>0),(Inputs!$D$28*Inputs!$C$15+Inputs!$D$29*Inputs!$C$15)*(1+Inputs!$D$30)/Inputs!$D$66,0) -> 0 | BH49: =IF(AND(53>Inputs!$D$65,53<=Inputs!$D$65+Inputs!$D$66,Inputs!$D$66>0),(Inputs!$D$28*Inputs!$C$15+Inputs!$D$29*Inputs!$C$15)*(1+Inputs!$D$30)/Inputs!$D$66,0) -> 0 | BI49: =IF(AND(54>Inputs!$D$65,54<=Inputs!$D$65+Inputs!$D$66,Inputs!$D$66>0),(Inputs!$D$28*Inputs!$C$15+Inputs!$D$29*Inputs!$C$15)*(1+Inputs!$D$30)/Inputs!$D$66,0) -> 0 | BJ49: =IF(AND(55>Inputs!$D$65,55<=Inputs!$D$65+Inputs!$D$66,Inputs!$D$66>0),(Inputs!$D$28*Inputs!$C$15+Inputs!$D$29*Inputs!$C$15)*(1+Inputs!$D$30)/Inputs!$D$66,0) -> 0 | BK49: =IF(AND(56>Inputs!$D$65,56<=Inputs!$D$65+Inputs!$D$66,Inputs!$D$66>0),(Inputs!$D$28*Inputs!$C$15+Inputs!$D$29*Inputs!$C$15)*(1+Inputs!$D$30)/Inputs!$D$66,0) -> 0 | BL49: =IF(AND(57>Inputs!$D$65,57<=Inputs!$D$65+Inputs!$D$66,Inputs!$D$66>0),(Inputs!$D$28*Inputs!$C$15+Inputs!$D$29*Inputs!$C$15)*(1+Inputs!$D$30)/Inputs!$D$66,0) -> 0 | BM49: =IF(AND(58>Inputs!$D$65,58<=Inputs!$D$65+Inputs!$D$66,Inputs!$D$66>0),(Inputs!$D$28*Inputs!$C$15+Inputs!$D$29*Inputs!$C$15)*(1+Inputs!$D$30)/Inputs!$D$66,0) -> 0 | BN49: =IF(AND(59>Inputs!$D$65,59<=Inputs!$D$65+Inputs!$D$66,Inputs!$D$66>0),(Inputs!$D$28*Inputs!$C$15+Inputs!$D$29*Inputs!$C$15)*(1+Inputs!$D$30)/Inputs!$D$66,0) -> 0 | BO49: =IF(AND(60>Inputs!$D$65,60<=Inputs!$D$65+Inputs!$D$66,Inputs!$D$66>0),(Inputs!$D$28*Inputs!$C$15+Inputs!$D$29*Inputs!$C$15)*(1+Inputs!$D$30)/Inputs!$D$66,0) -> 0
B50: Other costs | C50: =SUM(H50:BO50) -> 0 | H50: =IF(AND(1>Inputs!$D$65,1<=Inputs!$D$65+Inputs!$D$66,Inputs!$D$66>0),Inputs!$D$31/Inputs!$D$66,0) -> 0 | I50: =IF(AND(2>Inputs!$D$65,2<=Inputs!$D$65+Inputs!$D$66,Inputs!$D$66>0),Inputs!$D$31/Inputs!$D$66,0) -> 0 | J50: =IF(AND(3>Inputs!$D$65,3<=Inputs!$D$65+Inputs!$D$66,Inputs!$D$66>0),Inputs!$D$31/Inputs!$D$66,0) -> 0 | K50: =IF(AND(4>Inputs!$D$65,4<=Inputs!$D$65+Inputs!$D$66,Inputs!$D$66>0),Inputs!$D$31/Inputs!$D$66,0) -> 0 | L50: =IF(AND(5>Inputs!$D$65,5<=Inputs!$D$65+Inputs!$D$66,Inputs!$D$66>0),Inputs!$D$31/Inputs!$D$66,0) -> 0 | M50: =IF(AND(6>Inputs!$D$65,6<=Inputs!$D$65+Inputs!$D$66,Inputs!$D$66>0),Inputs!$D$31/Inputs!$D$66,0) -> 0 | N50: =IF(AND(7>Inputs!$D$65,7<=Inputs!$D$65+Inputs!$D$66,Inputs!$D$66>0),Inputs!$D$31/Inputs!$D$66,0) -> 0 | O50: =IF(AND(8>Inputs!$D$65,8<=Inputs!$D$65+Inputs!$D$66,Inputs!$D$66>0),Inputs!$D$31/Inputs!$D$66,0) -> 0 | P50: =IF(AND(9>Inputs!$D$65,9<=Inputs!$D$65+Inputs!$D$66,Inputs!$D$66>0),Inputs!$D$31/Inputs!$D$66,0) -> 0 | Q50: =IF(AND(10>Inputs!$D$65,10<=Inputs!$D$65+Inputs!$D$66,Inputs!$D$66>0),Inputs!$D$31/Inputs!$D$66,0) -> 0 | R50: =IF(AND(11>Inputs!$D$65,11<=Inputs!$D$65+Inputs!$D$66,Inputs!$D$66>0),Inputs!$D$31/Inputs!$D$66,0) -> 0 | S50: =IF(AND(12>Inputs!$D$65,12<=Inputs!$D$65+Inputs!$D$66,Inputs!$D$66>0),Inputs!$D$31/Inputs!$D$66,0) -> 0 | T50: =IF(AND(13>Inputs!$D$65,13<=Inputs!$D$65+Inputs!$D$66,Inputs!$D$66>0),Inputs!$D$31/Inputs!$D$66,0) -> 0 | U50: =IF(AND(14>Inputs!$D$65,14<=Inputs!$D$65+Inputs!$D$66,Inputs!$D$66>0),Inputs!$D$31/Inputs!$D$66,0) -> 0 | V50: =IF(AND(15>Inputs!$D$65,15<=Inputs!$D$65+Inputs!$D$66,Inputs!$D$66>0),Inputs!$D$31/Inputs!$D$66,0) -> 0 | W50: =IF(AND(16>Inputs!$D$65,16<=Inputs!$D$65+Inputs!$D$66,Inputs!$D$66>0),Inputs!$D$31/Inputs!$D$66,0) -> 0 | X50: =IF(AND(17>Inputs!$D$65,17<=Inputs!$D$65+Inputs!$D$66,Inputs!$D$66>0),Inputs!$D$31/Inputs!$D$66,0) -> 0 | Y50: =IF(AND(18>Inputs!$D$65,18<=Inputs!$D$65+Inputs!$D$66,Inputs!$D$66>0),Inputs!$D$31/Inputs!$D$66,0) -> 0 | Z50: =IF(AND(19>Inputs!$D$65,19<=Inputs!$D$65+Inputs!$D$66,Inputs!$D$66>0),Inputs!$D$31/Inputs!$D$66,0) -> 0 | AA50: =IF(AND(20>Inputs!$D$65,20<=Inputs!$D$65+Inputs!$D$66,Inputs!$D$66>0),Inputs!$D$31/Inputs!$D$66,0) -> 0 | AB50: =IF(AND(21>Inputs!$D$65,21<=Inputs!$D$65+Inputs!$D$66,Inputs!$D$66>0),Inputs!$D$31/Inputs!$D$66,0) -> 0 | AC50: =IF(AND(22>Inputs!$D$65,22<=Inputs!$D$65+Inputs!$D$66,Inputs!$D$66>0),Inputs!$D$31/Inputs!$D$66,0) -> 0 | AD50: =IF(AND(23>Inputs!$D$65,23<=Inputs!$D$65+Inputs!$D$66,Inputs!$D$66>0),Inputs!$D$31/Inputs!$D$66,0) -> 0 | AE50: =IF(AND(24>Inputs!$D$65,24<=Inputs!$D$65+Inputs!$D$66,Inputs!$D$66>0),Inputs!$D$31/Inputs!$D$66,0) -> 0 | AF50: =IF(AND(25>Inputs!$D$65,25<=Inputs!$D$65+Inputs!$D$66,Inputs!$D$66>0),Inputs!$D$31/Inputs!$D$66,0) -> 0 | AG50: =IF(AND(26>Inputs!$D$65,26<=Inputs!$D$65+Inputs!$D$66,Inputs!$D$66>0),Inputs!$D$31/Inputs!$D$66,0) -> 0 | AH50: =IF(AND(27>Inputs!$D$65,27<=Inputs!$D$65+Inputs!$D$66,Inputs!$D$66>0),Inputs!$D$31/Inputs!$D$66,0) -> 0 | AI50: =IF(AND(28>Inputs!$D$65,28<=Inputs!$D$65+Inputs!$D$66,Inputs!$D$66>0),Inputs!$D$31/Inputs!$D$66,0) -> 0 | AJ50: =IF(AND(29>Inputs!$D$65,29<=Inputs!$D$65+Inputs!$D$66,Inputs!$D$66>0),Inputs!$D$31/Inputs!$D$66,0) -> 0 | AK50: =IF(AND(30>Inputs!$D$65,30<=Inputs!$D$65+Inputs!$D$66,Inputs!$D$66>0),Inputs!$D$31/Inputs!$D$66,0) -> 0 | AL50: =IF(AND(31>Inputs!$D$65,31<=Inputs!$D$65+Inputs!$D$66,Inputs!$D$66>0),Inputs!$D$31/Inputs!$D$66,0) -> 0 | AM50: =IF(AND(32>Inputs!$D$65,32<=Inputs!$D$65+Inputs!$D$66,Inputs!$D$66>0),Inputs!$D$31/Inputs!$D$66,0) -> 0 | AN50: =IF(AND(33>Inputs!$D$65,33<=Inputs!$D$65+Inputs!$D$66,Inputs!$D$66>0),Inputs!$D$31/Inputs!$D$66,0) -> 0 | AO50: =IF(AND(34>Inputs!$D$65,34<=Inputs!$D$65+Inputs!$D$66,Inputs!$D$66>0),Inputs!$D$31/Inputs!$D$66,0) -> 0 | AP50: =IF(AND(35>Inputs!$D$65,35<=Inputs!$D$65+Inputs!$D$66,Inputs!$D$66>0),Inputs!$D$31/Inputs!$D$66,0) -> 0 | AQ50: =IF(AND(36>Inputs!$D$65,36<=Inputs!$D$65+Inputs!$D$66,Inputs!$D$66>0),Inputs!$D$31/Inputs!$D$66,0) -> 0 | AR50: =IF(AND(37>Inputs!$D$65,37<=Inputs!$D$65+Inputs!$D$66,Inputs!$D$66>0),Inputs!$D$31/Inputs!$D$66,0) -> 0 | AS50: =IF(AND(38>Inputs!$D$65,38<=Inputs!$D$65+Inputs!$D$66,Inputs!$D$66>0),Inputs!$D$31/Inputs!$D$66,0) -> 0 | AT50: =IF(AND(39>Inputs!$D$65,39<=Inputs!$D$65+Inputs!$D$66,Inputs!$D$66>0),Inputs!$D$31/Inputs!$D$66,0) -> 0 | AU50: =IF(AND(40>Inputs!$D$65,40<=Inputs!$D$65+Inputs!$D$66,Inputs!$D$66>0),Inputs!$D$31/Inputs!$D$66,0) -> 0 | AV50: =IF(AND(41>Inputs!$D$65,41<=Inputs!$D$65+Inputs!$D$66,Inputs!$D$66>0),Inputs!$D$31/Inputs!$D$66,0) -> 0 | AW50: =IF(AND(42>Inputs!$D$65,42<=Inputs!$D$65+Inputs!$D$66,Inputs!$D$66>0),Inputs!$D$31/Inputs!$D$66,0) -> 0 | AX50: =IF(AND(43>Inputs!$D$65,43<=Inputs!$D$65+Inputs!$D$66,Inputs!$D$66>0),Inputs!$D$31/Inputs!$D$66,0) -> 0 | AY50: =IF(AND(44>Inputs!$D$65,44<=Inputs!$D$65+Inputs!$D$66,Inputs!$D$66>0),Inputs!$D$31/Inputs!$D$66,0) -> 0 | AZ50: =IF(AND(45>Inputs!$D$65,45<=Inputs!$D$65+Inputs!$D$66,Inputs!$D$66>0),Inputs!$D$31/Inputs!$D$66,0) -> 0 | BA50: =IF(AND(46>Inputs!$D$65,46<=Inputs!$D$65+Inputs!$D$66,Inputs!$D$66>0),Inputs!$D$31/Inputs!$D$66,0) -> 0 | BB50: =IF(AND(47>Inputs!$D$65,47<=Inputs!$D$65+Inputs!$D$66,Inputs!$D$66>0),Inputs!$D$31/Inputs!$D$66,0) -> 0 | BC50: =IF(AND(48>Inputs!$D$65,48<=Inputs!$D$65+Inputs!$D$66,Inputs!$D$66>0),Inputs!$D$31/Inputs!$D$66,0) -> 0 | BD50: =IF(AND(49>Inputs!$D$65,49<=Inputs!$D$65+Inputs!$D$66,Inputs!$D$66>0),Inputs!$D$31/Inputs!$D$66,0) -> 0 | BE50: =IF(AND(50>Inputs!$D$65,50<=Inputs!$D$65+Inputs!$D$66,Inputs!$D$66>0),Inputs!$D$31/Inputs!$D$66,0) -> 0 | BF50: =IF(AND(51>Inputs!$D$65,51<=Inputs!$D$65+Inputs!$D$66,Inputs!$D$66>0),Inputs!$D$31/Inputs!$D$66,0) -> 0 | BG50: =IF(AND(52>Inputs!$D$65,52<=Inputs!$D$65+Inputs!$D$66,Inputs!$D$66>0),Inputs!$D$31/Inputs!$D$66,0) -> 0 | BH50: =IF(AND(53>Inputs!$D$65,53<=Inputs!$D$65+Inputs!$D$66,Inputs!$D$66>0),Inputs!$D$31/Inputs!$D$66,0) -> 0 | BI50: =IF(AND(54>Inputs!$D$65,54<=Inputs!$D$65+Inputs!$D$66,Inputs!$D$66>0),Inputs!$D$31/Inputs!$D$66,0) -> 0 | BJ50: =IF(AND(55>Inputs!$D$65,55<=Inputs!$D$65+Inputs!$D$66,Inputs!$D$66>0),Inputs!$D$31/Inputs!$D$66,0) -> 0 | BK50: =IF(AND(56>Inputs!$D$65,56<=Inputs!$D$65+Inputs!$D$66,Inputs!$D$66>0),Inputs!$D$31/Inputs!$D$66,0) -> 0 | BL50: =IF(AND(57>Inputs!$D$65,57<=Inputs!$D$65+Inputs!$D$66,Inputs!$D$66>0),Inputs!$D$31/Inputs!$D$66,0) -> 0 | BM50: =IF(AND(58>Inputs!$D$65,58<=Inputs!$D$65+Inputs!$D$66,Inputs!$D$66>0),Inputs!$D$31/Inputs!$D$66,0) -> 0 | BN50: =IF(AND(59>Inputs!$D$65,59<=Inputs!$D$65+Inputs!$D$66,Inputs!$D$66>0),Inputs!$D$31/Inputs!$D$66,0) -> 0 | BO50: =IF(AND(60>Inputs!$D$65,60<=Inputs!$D$65+Inputs!$D$66,Inputs!$D$66>0),Inputs!$D$31/Inputs!$D$66,0) -> 0
B51: Total Costs | C51: =SUM(H51:BO51) -> 0 | H51: =H48+H49+H50 -> 0 | I51: =I48+I49+I50 -> 0 | J51: =J48+J49+J50 -> 0 | K51: =K48+K49+K50 -> 0 | L51: =L48+L49+L50 -> 0 | M51: =M48+M49+M50 -> 0 | N51: =N48+N49+N50 -> 0 | O51: =O48+O49+O50 -> 0 | ... BO51: =BO48+BO49+BO50 -> 0
B53: SALES PROCEEDS
B55: Sales proceeds (reserve + construction + delivery) | C55: =SUM(H55:BO55) -> 0 | H55: =IF(AND(1>Inputs!$D$65+Inputs!$D$67,1<=Inputs!$D$65+Inputs!$D$66,Inputs!$D$66>Inputs!$D$67),Inputs!$C$18*(Inputs!$D$74+Inputs!$D$75)/MAX(Inputs!$D$66-Inputs!$D$67,1),0)+IF(1=Inputs!$D$65+Inputs!$D$66+Inputs!$D$77,Inputs!$C$18*Inputs!$D$76,0) -> 0 | I55: =IF(AND(2>Inputs!$D$65+Inputs!$D$67,2<=Inputs!$D$65+Inputs!$D$66,Inputs!$D$66>Inputs!$D$67),Inputs!$C$18*(Inputs!$D$74+Inputs!$D$75)/MAX(Inputs!$D$66-Inputs!$D$67,1),0)+IF(2=Inputs!$D$65+Inputs!$D$66+Inputs!$D$77,Inputs!$C$18*Inputs!$D$76,0) -> 0 | J55: =IF(AND(3>Inputs!$D$65+Inputs!$D$67,3<=Inputs!$D$65+Inputs!$D$66,Inputs!$D$66>Inputs!$D$67),Inputs!$C$18*(Inputs!$D$74+Inputs!$D$75)/MAX(Inputs!$D$66-Inputs!$D$67,1),0)+IF(3=Inputs!$D$65+Inputs!$D$66+Inputs!$D$77,Inputs!$C$18*Inputs!$D$76,0) -> 0 | K55: =IF(AND(4>Inputs!$D$65+Inputs!$D$67,4<=Inputs!$D$65+Inputs!$D$66,Inputs!$D$66>Inputs!$D$67),Inputs!$C$18*(Inputs!$D$74+Inputs!$D$75)/MAX(Inputs!$D$66-Inputs!$D$67,1),0)+IF(4=Inputs!$D$65+Inputs!$D$66+Inputs!$D$77,Inputs!$C$18*Inputs!$D$76,0) -> 0 | L55: =IF(AND(5>Inputs!$D$65+Inputs!$D$67,5<=Inputs!$D$65+Inputs!$D$66,Inputs!$D$66>Inputs!$D$67),Inputs!$C$18*(Inputs!$D$74+Inputs!$D$75)/MAX(Inputs!$D$66-Inputs!$D$67,1),0)+IF(5=Inputs!$D$65+Inputs!$D$66+Inputs!$D$77,Inputs!$C$18*Inputs!$D$76,0) -> 0 | M55: =IF(AND(6>Inputs!$D$65+Inputs!$D$67,6<=Inputs!$D$65+Inputs!$D$66,Inputs!$D$66>Inputs!$D$67),Inputs!$C$18*(Inputs!$D$74+Inputs!$D$75)/MAX(Inputs!$D$66-Inputs!$D$67,1),0)+IF(6=Inputs!$D$65+Inputs!$D$66+Inputs!$D$77,Inputs!$C$18*Inputs!$D$76,0) -> 0 | N55: =IF(AND(7>Inputs!$D$65+Inputs!$D$67,7<=Inputs!$D$65+Inputs!$D$66,Inputs!$D$66>Inputs!$D$67),Inputs!$C$18*(Inputs!$D$74+Inputs!$D$75)/MAX(Inputs!$D$66-Inputs!$D$67,1),0)+IF(7=Inputs!$D$65+Inputs!$D$66+Inputs!$D$77,Inputs!$C$18*Inputs!$D$76,0) -> 0 | O55: =IF(AND(8>Inputs!$D$65+Inputs!$D$67,8<=Inputs!$D$65+Inputs!$D$66,Inputs!$D$66>Inputs!$D$67),Inputs!$C$18*(Inputs!$D$74+Inputs!$D$75)/MAX(Inputs!$D$66-Inputs!$D$67,1),0)+IF(8=Inputs!$D$65+Inputs!$D$66+Inputs!$D$77,Inputs!$C$18*Inputs!$D$76,0) -> 0 | P55: =IF(AND(9>Inputs!$D$65+Inputs!$D$67,9<=Inputs!$D$65+Inputs!$D$66,Inputs!$D$66>Inputs!$D$67),Inputs!$C$18*(Inputs!$D$74+Inputs!$D$75)/MAX(Inputs!$D$66-Inputs!$D$67,1),0)+IF(9=Inputs!$D$65+Inputs!$D$66+Inputs!$D$77,Inputs!$C$18*Inputs!$D$76,0) -> 0 | Q55: =IF(AND(10>Inputs!$D$65+Inputs!$D$67,10<=Inputs!$D$65+Inputs!$D$66,Inputs!$D$66>Inputs!$D$67),Inputs!$C$18*(Inputs!$D$74+Inputs!$D$75)/MAX(Inputs!$D$66-Inputs!$D$67,1),0)+IF(10=Inputs!$D$65+Inputs!$D$66+Inputs!$D$77,Inputs!$C$18*Inputs!$D$76,0) -> 0 | R55: =IF(AND(11>Inputs!$D$65+Inputs!$D$67,11<=Inputs!$D$65+Inputs!$D$66,Inputs!$D$66>Inputs!$D$67),Inputs!$C$18*(Inputs!$D$74+Inputs!$D$75)/MAX(Inputs!$D$66-Inputs!$D$67,1),0)+IF(11=Inputs!$D$65+Inputs!$D$66+Inputs!$D$77,Inputs!$C$18*Inputs!$D$76,0) -> 0 | S55: =IF(AND(12>Inputs!$D$65+Inputs!$D$67,12<=Inputs!$D$65+Inputs!$D$66,Inputs!$D$66>Inputs!$D$67),Inputs!$C$18*(Inputs!$D$74+Inputs!$D$75)/MAX(Inputs!$D$66-Inputs!$D$67,1),0)+IF(12=Inputs!$D$65+Inputs!$D$66+Inputs!$D$77,Inputs!$C$18*Inputs!$D$76,0) -> 0 | T55: =IF(AND(13>Inputs!$D$65+Inputs!$D$67,13<=Inputs!$D$65+Inputs!$D$66,Inputs!$D$66>Inputs!$D$67),Inputs!$C$18*(Inputs!$D$74+Inputs!$D$75)/MAX(Inputs!$D$66-Inputs!$D$67,1),0)+IF(13=Inputs!$D$65+Inputs!$D$66+Inputs!$D$77,Inputs!$C$18*Inputs!$D$76,0) -> 0 | U55: =IF(AND(14>Inputs!$D$65+Inputs!$D$67,14<=Inputs!$D$65+Inputs!$D$66,Inputs!$D$66>Inputs!$D$67),Inputs!$C$18*(Inputs!$D$74+Inputs!$D$75)/MAX(Inputs!$D$66-Inputs!$D$67,1),0)+IF(14=Inputs!$D$65+Inputs!$D$66+Inputs!$D$77,Inputs!$C$18*Inputs!$D$76,0) -> 0 | V55: =IF(AND(15>Inputs!$D$65+Inputs!$D$67,15<=Inputs!$D$65+Inputs!$D$66,Inputs!$D$66>Inputs!$D$67),Inputs!$C$18*(Inputs!$D$74+Inputs!$D$75)/MAX(Inputs!$D$66-Inputs!$D$67,1),0)+IF(15=Inputs!$D$65+Inputs!$D$66+Inputs!$D$77,Inputs!$C$18*Inputs!$D$76,0) -> 0 | W55: =IF(AND(16>Inputs!$D$65+Inputs!$D$67,16<=Inputs!$D$65+Inputs!$D$66,Inputs!$D$66>Inputs!$D$67),Inputs!$C$18*(Inputs!$D$74+Inputs!$D$75)/MAX(Inputs!$D$66-Inputs!$D$67,1),0)+IF(16=Inputs!$D$65+Inputs!$D$66+Inputs!$D$77,Inputs!$C$18*Inputs!$D$76,0) -> 0 | X55: =IF(AND(17>Inputs!$D$65+Inputs!$D$67,17<=Inputs!$D$65+Inputs!$D$66,Inputs!$D$66>Inputs!$D$67),Inputs!$C$18*(Inputs!$D$74+Inputs!$D$75)/MAX(Inputs!$D$66-Inputs!$D$67,1),0)+IF(17=Inputs!$D$65+Inputs!$D$66+Inputs!$D$77,Inputs!$C$18*Inputs!$D$76,0) -> 0 | Y55: =IF(AND(18>Inputs!$D$65+Inputs!$D$67,18<=Inputs!$D$65+Inputs!$D$66,Inputs!$D$66>Inputs!$D$67),Inputs!$C$18*(Inputs!$D$74+Inputs!$D$75)/MAX(Inputs!$D$66-Inputs!$D$67,1),0)+IF(18=Inputs!$D$65+Inputs!$D$66+Inputs!$D$77,Inputs!$C$18*Inputs!$D$76,0) -> 0 | Z55: =IF(AND(19>Inputs!$D$65+Inputs!$D$67,19<=Inputs!$D$65+Inputs!$D$66,Inputs!$D$66>Inputs!$D$67),Inputs!$C$18*(Inputs!$D$74+Inputs!$D$75)/MAX(Inputs!$D$66-Inputs!$D$67,1),0)+IF(19=Inputs!$D$65+Inputs!$D$66+Inputs!$D$77,Inputs!$C$18*Inputs!$D$76,0) -> 0 | AA55: =IF(AND(20>Inputs!$D$65+Inputs!$D$67,20<=Inputs!$D$65+Inputs!$D$66,Inputs!$D$66>Inputs!$D$67),Inputs!$C$18*(Inputs!$D$74+Inputs!$D$75)/MAX(Inputs!$D$66-Inputs!$D$67,1),0)+IF(20=Inputs!$D$65+Inputs!$D$66+Inputs!$D$77,Inputs!$C$18*Inputs!$D$76,0) -> 0 | AB55: =IF(AND(21>Inputs!$D$65+Inputs!$D$67,21<=Inputs!$D$65+Inputs!$D$66,Inputs!$D$66>Inputs!$D$67),Inputs!$C$18*(Inputs!$D$74+Inputs!$D$75)/MAX(Inputs!$D$66-Inputs!$D$67,1),0)+IF(21=Inputs!$D$65+Inputs!$D$66+Inputs!$D$77,Inputs!$C$18*Inputs!$D$76,0) -> 0 | AC55: =IF(AND(22>Inputs!$D$65+Inputs!$D$67,22<=Inputs!$D$65+Inputs!$D$66,Inputs!$D$66>Inputs!$D$67),Inputs!$C$18*(Inputs!$D$74+Inputs!$D$75)/MAX(Inputs!$D$66-Inputs!$D$67,1),0)+IF(22=Inputs!$D$65+Inputs!$D$66+Inputs!$D$77,Inputs!$C$18*Inputs!$D$76,0) -> 0 | AD55: =IF(AND(23>Inputs!$D$65+Inputs!$D$67,23<=Inputs!$D$65+Inputs!$D$66,Inputs!$D$66>Inputs!$D$67),Inputs!$C$18*(Inputs!$D$74+Inputs!$D$75)/MAX(Inputs!$D$66-Inputs!$D$67,1),0)+IF(23=Inputs!$D$65+Inputs!$D$66+Inputs!$D$77,Inputs!$C$18*Inputs!$D$76,0) -> 0 | AE55: =IF(AND(24>Inputs!$D$65+Inputs!$D$67,24<=Inputs!$D$65+Inputs!$D$66,Inputs!$D$66>Inputs!$D$67),Inputs!$C$18*(Inputs!$D$74+Inputs!$D$75)/MAX(Inputs!$D$66-Inputs!$D$67,1),0)+IF(24=Inputs!$D$65+Inputs!$D$66+Inputs!$D$77,Inputs!$C$18*Inputs!$D$76,0) -> 0 | AF55: =IF(AND(25>Inputs!$D$65+Inputs!$D$67,25<=Inputs!$D$65+Inputs!$D$66,Inputs!$D$66>Inputs!$D$67),Inputs!$C$18*(Inputs!$D$74+Inputs!$D$75)/MAX(Inputs!$D$66-Inputs!$D$67,1),0)+IF(25=Inputs!$D$65+Inputs!$D$66+Inputs!$D$77,Inputs!$C$18*Inputs!$D$76,0) -> 0 | AG55: =IF(AND(26>Inputs!$D$65+Inputs!$D$67,26<=Inputs!$D$65+Inputs!$D$66,Inputs!$D$66>Inputs!$D$67),Inputs!$C$18*(Inputs!$D$74+Inputs!$D$75)/MAX(Inputs!$D$66-Inputs!$D$67,1),0)+IF(26=Inputs!$D$65+Inputs!$D$66+Inputs!$D$77,Inputs!$C$18*Inputs!$D$76,0) -> 0 | AH55: =IF(AND(27>Inputs!$D$65+Inputs!$D$67,27<=Inputs!$D$65+Inputs!$D$66,Inputs!$D$66>Inputs!$D$67),Inputs!$C$18*(Inputs!$D$74+Inputs!$D$75)/MAX(Inputs!$D$66-Inputs!$D$67,1),0)+IF(27=Inputs!$D$65+Inputs!$D$66+Inputs!$D$77,Inputs!$C$18*Inputs!$D$76,0) -> 0 | AI55: =IF(AND(28>Inputs!$D$65+Inputs!$D$67,28<=Inputs!$D$65+Inputs!$D$66,Inputs!$D$66>Inputs!$D$67),Inputs!$C$18*(Inputs!$D$74+Inputs!$D$75)/MAX(Inputs!$D$66-Inputs!$D$67,1),0)+IF(28=Inputs!$D$65+Inputs!$D$66+Inputs!$D$77,Inputs!$C$18*Inputs!$D$76,0) -> 0 | AJ55: =IF(AND(29>Inputs!$D$65+Inputs!$D$67,29<=Inputs!$D$65+Inputs!$D$66,Inputs!$D$66>Inputs!$D$67),Inputs!$C$18*(Inputs!$D$74+Inputs!$D$75)/MAX(Inputs!$D$66-Inputs!$D$67,1),0)+IF(29=Inputs!$D$65+Inputs!$D$66+Inputs!$D$77,Inputs!$C$18*Inputs!$D$76,0) -> 0 | AK55: =IF(AND(30>Inputs!$D$65+Inputs!$D$67,30<=Inputs!$D$65+Inputs!$D$66,Inputs!$D$66>Inputs!$D$67),Inputs!$C$18*(Inputs!$D$74+Inputs!$D$75)/MAX(Inputs!$D$66-Inputs!$D$67,1),0)+IF(30=Inputs!$D$65+Inputs!$D$66+Inputs!$D$77,Inputs!$C$18*Inputs!$D$76,0) -> 0 | AL55: =IF(AND(31>Inputs!$D$65+Inputs!$D$67,31<=Inputs!$D$65+Inputs!$D$66,Inputs!$D$66>Inputs!$D$67),Inputs!$C$18*(Inputs!$D$74+Inputs!$D$75)/MAX(Inputs!$D$66-Inputs!$D$67,1),0)+IF(31=Inputs!$D$65+Inputs!$D$66+Inputs!$D$77,Inputs!$C$18*Inputs!$D$76,0) -> 0 | AM55: =IF(AND(32>Inputs!$D$65+Inputs!$D$67,32<=Inputs!$D$65+Inputs!$D$66,Inputs!$D$66>Inputs!$D$67),Inputs!$C$18*(Inputs!$D$74+Inputs!$D$75)/MAX(Inputs!$D$66-Inputs!$D$67,1),0)+IF(32=Inputs!$D$65+Inputs!$D$66+Inputs!$D$77,Inputs!$C$18*Inputs!$D$76,0) -> 0 | AN55: =IF(AND(33>Inputs!$D$65+Inputs!$D$67,33<=Inputs!$D$65+Inputs!$D$66,Inputs!$D$66>Inputs!$D$67),Inputs!$C$18*(Inputs!$D$74+Inputs!$D$75)/MAX(Inputs!$D$66-Inputs!$D$67,1),0)+IF(33=Inputs!$D$65+Inputs!$D$66+Inputs!$D$77,Inputs!$C$18*Inputs!$D$76,0) -> 0 | AO55: =IF(AND(34>Inputs!$D$65+Inputs!$D$67,34<=Inputs!$D$65+Inputs!$D$66,Inputs!$D$66>Inputs!$D$67),Inputs!$C$18*(Inputs!$D$74+Inputs!$D$75)/MAX(Inputs!$D$66-Inputs!$D$67,1),0)+IF(34=Inputs!$D$65+Inputs!$D$66+Inputs!$D$77,Inputs!$C$18*Inputs!$D$76,0) -> 0 | AP55: =IF(AND(35>Inputs!$D$65+Inputs!$D$67,35<=Inputs!$D$65+Inputs!$D$66,Inputs!$D$66>Inputs!$D$67),Inputs!$C$18*(Inputs!$D$74+Inputs!$D$75)/MAX(Inputs!$D$66-Inputs!$D$67,1),0)+IF(35=Inputs!$D$65+Inputs!$D$66+Inputs!$D$77,Inputs!$C$18*Inputs!$D$76,0) -> 0 | AQ55: =IF(AND(36>Inputs!$D$65+Inputs!$D$67,36<=Inputs!$D$65+Inputs!$D$66,Inputs!$D$66>Inputs!$D$67),Inputs!$C$18*(Inputs!$D$74+Inputs!$D$75)/MAX(Inputs!$D$66-Inputs!$D$67,1),0)+IF(36=Inputs!$D$65+Inputs!$D$66+Inputs!$D$77,Inputs!$C$18*Inputs!$D$76,0) -> 0 | AR55: =IF(AND(37>Inputs!$D$65+Inputs!$D$67,37<=Inputs!$D$65+Inputs!$D$66,Inputs!$D$66>Inputs!$D$67),Inputs!$C$18*(Inputs!$D$74+Inputs!$D$75)/MAX(Inputs!$D$66-Inputs!$D$67,1),0)+IF(37=Inputs!$D$65+Inputs!$D$66+Inputs!$D$77,Inputs!$C$18*Inputs!$D$76,0) -> 0 | AS55: =IF(AND(38>Inputs!$D$65+Inputs!$D$67,38<=Inputs!$D$65+Inputs!$D$66,Inputs!$D$66>Inputs!$D$67),Inputs!$C$18*(Inputs!$D$74+Inputs!$D$75)/MAX(Inputs!$D$66-Inputs!$D$67,1),0)+IF(38=Inputs!$D$65+Inputs!$D$66+Inputs!$D$77,Inputs!$C$18*Inputs!$D$76,0) -> 0 | AT55: =IF(AND(39>Inputs!$D$65+Inputs!$D$67,39<=Inputs!$D$65+Inputs!$D$66,Inputs!$D$66>Inputs!$D$67),Inputs!$C$18*(Inputs!$D$74+Inputs!$D$75)/MAX(Inputs!$D$66-Inputs!$D$67,1),0)+IF(39=Inputs!$D$65+Inputs!$D$66+Inputs!$D$77,Inputs!$C$18*Inputs!$D$76,0) -> 0 | AU55: =IF(AND(40>Inputs!$D$65+Inputs!$D$67,40<=Inputs!$D$65+Inputs!$D$66,Inputs!$D$66>Inputs!$D$67),Inputs!$C$18*(Inputs!$D$74+Inputs!$D$75)/MAX(Inputs!$D$66-Inputs!$D$67,1),0)+IF(40=Inputs!$D$65+Inputs!$D$66+Inputs!$D$77,Inputs!$C$18*Inputs!$D$76,0) -> 0 | AV55: =IF(AND(41>Inputs!$D$65+Inputs!$D$67,41<=Inputs!$D$65+Inputs!$D$66,Inputs!$D$66>Inputs!$D$67),Inputs!$C$18*(Inputs!$D$74+Inputs!$D$75)/MAX(Inputs!$D$66-Inputs!$D$67,1),0)+IF(41=Inputs!$D$65+Inputs!$D$66+Inputs!$D$77,Inputs!$C$18*Inputs!$D$76,0) -> 0 | AW55: =IF(AND(42>Inputs!$D$65+Inputs!$D$67,42<=Inputs!$D$65+Inputs!$D$66,Inputs!$D$66>Inputs!$D$67),Inputs!$C$18*(Inputs!$D$74+Inputs!$D$75)/MAX(Inputs!$D$66-Inputs!$D$67,1),0)+IF(42=Inputs!$D$65+Inputs!$D$66+Inputs!$D$77,Inputs!$C$18*Inputs!$D$76,0) -> 0 | AX55: =IF(AND(43>Inputs!$D$65+Inputs!$D$67,43<=Inputs!$D$65+Inputs!$D$66,Inputs!$D$66>Inputs!$D$67),Inputs!$C$18*(Inputs!$D$74+Inputs!$D$75)/MAX(Inputs!$D$66-Inputs!$D$67,1),0)+IF(43=Inputs!$D$65+Inputs!$D$66+Inputs!$D$77,Inputs!$C$18*Inputs!$D$76,0) -> 0 | AY55: =IF(AND(44>Inputs!$D$65+Inputs!$D$67,44<=Inputs!$D$65+Inputs!$D$66,Inputs!$D$66>Inputs!$D$67),Inputs!$C$18*(Inputs!$D$74+Inputs!$D$75)/MAX(Inputs!$D$66-Inputs!$D$67,1),0)+IF(44=Inputs!$D$65+Inputs!$D$66+Inputs!$D$77,Inputs!$C$18*Inputs!$D$76,0) -> 0 | AZ55: =IF(AND(45>Inputs!$D$65+Inputs!$D$67,45<=Inputs!$D$65+Inputs!$D$66,Inputs!$D$66>Inputs!$D$67),Inputs!$C$18*(Inputs!$D$74+Inputs!$D$75)/MAX(Inputs!$D$66-Inputs!$D$67,1),0)+IF(45=Inputs!$D$65+Inputs!$D$66+Inputs!$D$77,Inputs!$C$18*Inputs!$D$76,0) -> 0 | BA55: =IF(AND(46>Inputs!$D$65+Inputs!$D$67,46<=Inputs!$D$65+Inputs!$D$66,Inputs!$D$66>Inputs!$D$67),Inputs!$C$18*(Inputs!$D$74+Inputs!$D$75)/MAX(Inputs!$D$66-Inputs!$D$67,1),0)+IF(46=Inputs!$D$65+Inputs!$D$66+Inputs!$D$77,Inputs!$C$18*Inputs!$D$76,0) -> 0 | BB55: =IF(AND(47>Inputs!$D$65+Inputs!$D$67,47<=Inputs!$D$65+Inputs!$D$66,Inputs!$D$66>Inputs!$D$67),Inputs!$C$18*(Inputs!$D$74+Inputs!$D$75)/MAX(Inputs!$D$66-Inputs!$D$67,1),0)+IF(47=Inputs!$D$65+Inputs!$D$66+Inputs!$D$77,Inputs!$C$18*Inputs!$D$76,0) -> 0 | BC55: =IF(AND(48>Inputs!$D$65+Inputs!$D$67,48<=Inputs!$D$65+Inputs!$D$66,Inputs!$D$66>Inputs!$D$67),Inputs!$C$18*(Inputs!$D$74+Inputs!$D$75)/MAX(Inputs!$D$66-Inputs!$D$67,1),0)+IF(48=Inputs!$D$65+Inputs!$D$66+Inputs!$D$77,Inputs!$C$18*Inputs!$D$76,0) -> 0 | BD55: =IF(AND(49>Inputs!$D$65+Inputs!$D$67,49<=Inputs!$D$65+Inputs!$D$66,Inputs!$D$66>Inputs!$D$67),Inputs!$C$18*(Inputs!$D$74+Inputs!$D$75)/MAX(Inputs!$D$66-Inputs!$D$67,1),0)+IF(49=Inputs!$D$65+Inputs!$D$66+Inputs!$D$77,Inputs!$C$18*Inputs!$D$76,0) -> 0 | BE55: =IF(AND(50>Inputs!$D$65+Inputs!$D$67,50<=Inputs!$D$65+Inputs!$D$66,Inputs!$D$66>Inputs!$D$67),Inputs!$C$18*(Inputs!$D$74+Inputs!$D$75)/MAX(Inputs!$D$66-Inputs!$D$67,1),0)+IF(50=Inputs!$D$65+Inputs!$D$66+Inputs!$D$77,Inputs!$C$18*Inputs!$D$76,0) -> 0 | BF55: =IF(AND(51>Inputs!$D$65+Inputs!$D$67,51<=Inputs!$D$65+Inputs!$D$66,Inputs!$D$66>Inputs!$D$67),Inputs!$C$18*(Inputs!$D$74+Inputs!$D$75)/MAX(Inputs!$D$66-Inputs!$D$67,1),0)+IF(51=Inputs!$D$65+Inputs!$D$66+Inputs!$D$77,Inputs!$C$18*Inputs!$D$76,0) -> 0 | BG55: =IF(AND(52>Inputs!$D$65+Inputs!$D$67,52<=Inputs!$D$65+Inputs!$D$66,Inputs!$D$66>Inputs!$D$67),Inputs!$C$18*(Inputs!$D$74+Inputs!$D$75)/MAX(Inputs!$D$66-Inputs!$D$67,1),0)+IF(52=Inputs!$D$65+Inputs!$D$66+Inputs!$D$77,Inputs!$C$18*Inputs!$D$76,0) -> 0 | BH55: =IF(AND(53>Inputs!$D$65+Inputs!$D$67,53<=Inputs!$D$65+Inputs!$D$66,Inputs!$D$66>Inputs!$D$67),Inputs!$C$18*(Inputs!$D$74+Inputs!$D$75)/MAX(Inputs!$D$66-Inputs!$D$67,1),0)+IF(53=Inputs!$D$65+Inputs!$D$66+Inputs!$D$77,Inputs!$C$18*Inputs!$D$76,0) -> 0 | BI55: =IF(AND(54>Inputs!$D$65+Inputs!$D$67,54<=Inputs!$D$65+Inputs!$D$66,Inputs!$D$66>Inputs!$D$67),Inputs!$C$18*(Inputs!$D$74+Inputs!$D$75)/MAX(Inputs!$D$66-Inputs!$D$67,1),0)+IF(54=Inputs!$D$65+Inputs!$D$66+Inputs!$D$77,Inputs!$C$18*Inputs!$D$76,0) -> 0 | BJ55: =IF(AND(55>Inputs!$D$65+Inputs!$D$67,55<=Inputs!$D$65+Inputs!$D$66,Inputs!$D$66>Inputs!$D$67),Inputs!$C$18*(Inputs!$D$74+Inputs!$D$75)/MAX(Inputs!$D$66-Inputs!$D$67,1),0)+IF(55=Inputs!$D$65+Inputs!$D$66+Inputs!$D$77,Inputs!$C$18*Inputs!$D$76,0) -> 0 | BK55: =IF(AND(56>Inputs!$D$65+Inputs!$D$67,56<=Inputs!$D$65+Inputs!$D$66,Inputs!$D$66>Inputs!$D$67),Inputs!$C$18*(Inputs!$D$74+Inputs!$D$75)/MAX(Inputs!$D$66-Inputs!$D$67,1),0)+IF(56=Inputs!$D$65+Inputs!$D$66+Inputs!$D$77,Inputs!$C$18*Inputs!$D$76,0) -> 0 | BL55: =IF(AND(57>Inputs!$D$65+Inputs!$D$67,57<=Inputs!$D$65+Inputs!$D$66,Inputs!$D$66>Inputs!$D$67),Inputs!$C$18*(Inputs!$D$74+Inputs!$D$75)/MAX(Inputs!$D$66-Inputs!$D$67,1),0)+IF(57=Inputs!$D$65+Inputs!$D$66+Inputs!$D$77,Inputs!$C$18*Inputs!$D$76,0) -> 0 | BM55: =IF(AND(58>Inputs!$D$65+Inputs!$D$67,58<=Inputs!$D$65+Inputs!$D$66,Inputs!$D$66>Inputs!$D$67),Inputs!$C$18*(Inputs!$D$74+Inputs!$D$75)/MAX(Inputs!$D$66-Inputs!$D$67,1),0)+IF(58=Inputs!$D$65+Inputs!$D$66+Inputs!$D$77,Inputs!$C$18*Inputs!$D$76,0) -> 0 | BN55: =IF(AND(59>Inputs!$D$65+Inputs!$D$67,59<=Inputs!$D$65+Inputs!$D$66,Inputs!$D$66>Inputs!$D$67),Inputs!$C$18*(Inputs!$D$74+Inputs!$D$75)/MAX(Inputs!$D$66-Inputs!$D$67,1),0)+IF(59=Inputs!$D$65+Inputs!$D$66+Inputs!$D$77,Inputs!$C$18*Inputs!$D$76,0) -> 0 | BO55: =IF(AND(60>Inputs!$D$65+Inputs!$D$67,60<=Inputs!$D$65+Inputs!$D$66,Inputs!$D$66>Inputs!$D$67),Inputs!$C$18*(Inputs!$D$74+Inputs!$D$75)/MAX(Inputs!$D$66-Inputs!$D$67,1),0)+IF(60=Inputs!$D$65+Inputs!$D$66+Inputs!$D$77,Inputs!$C$18*Inputs!$D$76,0) -> 0
C66: max
B67: LTC
B68: LTV
B69: LOAN MECHANICS
B72: Opening fee (capitalized) | C72: =SUM(H72:BO72) -> 0 | H72: =IF(1=1,Inputs!$D$55*Inputs!$D$58,0) -> 0 | I72: =IF(2=1,Inputs!$D$55*Inputs!$D$58,0) -> 0 | J72: =IF(3=1,Inputs!$D$55*Inputs!$D$58,0) -> 0 | K72: =IF(4=1,Inputs!$D$55*Inputs!$D$58,0) -> 0 | L72: =IF(5=1,Inputs!$D$55*Inputs!$D$58,0) -> 0 | M72: =IF(6=1,Inputs!$D$55*Inputs!$D$58,0) -> 0 | N72: =IF(7=1,Inputs!$D$55*Inputs!$D$58,0) -> 0 | O72: =IF(8=1,Inputs!$D$55*Inputs!$D$58,0) -> 0 | P72: =IF(9=1,Inputs!$D$55*Inputs!$D$58,0) -> 0 | Q72: =IF(10=1,Inputs!$D$55*Inputs!$D$58,0) -> 0 | R72: =IF(11=1,Inputs!$D$55*Inputs!$D$58,0) -> 0 | S72: =IF(12=1,Inputs!$D$55*Inputs!$D$58,0) -> 0 | T72: =IF(13=1,Inputs!$D$55*Inputs!$D$58,0) -> 0 | U72: =IF(14=1,Inputs!$D$55*Inputs!$D$58,0) -> 0 | V72: =IF(15=1,Inputs!$D$55*Inputs!$D$58,0) -> 0 | W72: =IF(16=1,Inputs!$D$55*Inputs!$D$58,0) -> 0 | X72: =IF(17=1,Inputs!$D$55*Inputs!$D$58,0) -> 0 | Y72: =IF(18=1,Inputs!$D$55*Inputs!$D$58,0) -> 0 | Z72: =IF(19=1,Inputs!$D$55*Inputs!$D$58,0) -> 0 | AA72: =IF(20=1,Inputs!$D$55*Inputs!$D$58,0) -> 0 | AB72: =IF(21=1,Inputs!$D$55*Inputs!$D$58,0) -> 0 | AC72: =IF(22=1,Inputs!$D$55*Inputs!$D$58,0) -> 0 | AD72: =IF(23=1,Inputs!$D$55*Inputs!$D$58,0) -> 0 | AE72: =IF(24=1,Inputs!$D$55*Inputs!$D$58,0) -> 0 | AF72: =IF(25=1,Inputs!$D$55*Inputs!$D$58,0) -> 0 | AG72: =IF(26=1,Inputs!$D$55*Inputs!$D$58,0) -> 0 | AH72: =IF(27=1,Inputs!$D$55*Inputs!$D$58,0) -> 0 | AI72: =IF(28=1,Inputs!$D$55*Inputs!$D$58,0) -> 0 | AJ72: =IF(29=1,Inputs!$D$55*Inputs!$D$58,0) -> 0 | AK72: =IF(30=1,Inputs!$D$55*Inputs!$D$58,0) -> 0 | AL72: =IF(31=1,Inputs!$D$55*Inputs!$D$58,0) -> 0 | AM72: =IF(32=1,Inputs!$D$55*Inputs!$D$58,0) -> 0 | AN72: =IF(33=1,Inputs!$D$55*Inputs!$D$58,0) -> 0 | AO72: =IF(34=1,Inputs!$D$55*Inputs!$D$58,0) -> 0 | AP72: =IF(35=1,Inputs!$D$55*Inputs!$D$58,0) -> 0 | AQ72: =IF(36=1,Inputs!$D$55*Inputs!$D$58,0) -> 0 | AR72: =IF(37=1,Inputs!$D$55*Inputs!$D$58,0) -> 0 | AS72: =IF(38=1,Inputs!$D$55*Inputs!$D$58,0) -> 0 | AT72: =IF(39=1,Inputs!$D$55*Inputs!$D$58,0) -> 0 | AU72: =IF(40=1,Inputs!$D$55*Inputs!$D$58,0) -> 0 | AV72: =IF(41=1,Inputs!$D$55*Inputs!$D$58,0) -> 0 | AW72: =IF(42=1,Inputs!$D$55*Inputs!$D$58,0) -> 0 | AX72: =IF(43=1,Inputs!$D$55*Inputs!$D$58,0) -> 0 | AY72: =IF(44=1,Inputs!$D$55*Inputs!$D$58,0) -> 0 | AZ72: =IF(45=1,Inputs!$D$55*Inputs!$D$58,0) -> 0 | BA72: =IF(46=1,Inputs!$D$55*Inputs!$D$58,0) -> 0 | BB72: =IF(47=1,Inputs!$D$55*Inputs!$D$58,0) -> 0 | BC72: =IF(48=1,Inputs!$D$55*Inputs!$D$58,0) -> 0 | BD72: =IF(49=1,Inputs!$D$55*Inputs!$D$58,0) -> 0 | BE72: =IF(50=1,Inputs!$D$55*Inputs!$D$58,0) -> 0 | BF72: =IF(51=1,Inputs!$D$55*Inputs!$D$58,0) -> 0 | BG72: =IF(52=1,Inputs!$D$55*Inputs!$D$58,0) -> 0 | BH72: =IF(53=1,Inputs!$D$55*Inputs!$D$58,0) -> 0 | BI72: =IF(54=1,Inputs!$D$55*Inputs!$D$58,0) -> 0 | BJ72: =IF(55=1,Inputs!$D$55*Inputs!$D$58,0) -> 0 | BK72: =IF(56=1,Inputs!$D$55*Inputs!$D$58,0) -> 0 | BL72: =IF(57=1,Inputs!$D$55*Inputs!$D$58,0) -> 0 | BM72: =IF(58=1,Inputs!$D$55*Inputs!$D$58,0) -> 0 | BN72: =IF(59=1,Inputs!$D$55*Inputs!$D$58,0) -> 0 | BO72: =IF(60=1,Inputs!$D$55*Inputs!$D$58,0) -> 0
B73: Loan drawdowns (to lender's usage) | C73: =SUM(H73:BO73) -> 0 | H73: =IFERROR(H51*MIN(1,Inputs!$D$55/C51),0) -> 0 | I73: =IFERROR(I51*MIN(1,Inputs!$D$55/C51),0) -> 0 | J73: =IFERROR(J51*MIN(1,Inputs!$D$55/C51),0) -> 0 | K73: =IFERROR(K51*MIN(1,Inputs!$D$55/C51),0) -> 0 | L73: =IFERROR(L51*MIN(1,Inputs!$D$55/C51),0) -> 0 | M73: =IFERROR(M51*MIN(1,Inputs!$D$55/C51),0) -> 0 | N73: =IFERROR(N51*MIN(1,Inputs!$D$55/C51),0) -> 0 | O73: =IFERROR(O51*MIN(1,Inputs!$D$55/C51),0) -> 0 | P73: =IFERROR(P51*MIN(1,Inputs!$D$55/C51),0) -> 0 | Q73: =IFERROR(Q51*MIN(1,Inputs!$D$55/C51),0) -> 0 | R73: =IFERROR(R51*MIN(1,Inputs!$D$55/C51),0) -> 0 | S73: =IFERROR(S51*MIN(1,Inputs!$D$55/C51),0) -> 0 | T73: =IFERROR(T51*MIN(1,Inputs!$D$55/C51),0) -> 0 | U73: =IFERROR(U51*MIN(1,Inputs!$D$55/C51),0) -> 0 | V73: =IFERROR(V51*MIN(1,Inputs!$D$55/C51),0) -> 0 | W73: =IFERROR(W51*MIN(1,Inputs!$D$55/C51),0) -> 0 | X73: =IFERROR(X51*MIN(1,Inputs!$D$55/C51),0) -> 0 | Y73: =IFERROR(Y51*MIN(1,Inputs!$D$55/C51),0) -> 0 | Z73: =IFERROR(Z51*MIN(1,Inputs!$D$55/C51),0) -> 0 | AA73: =IFERROR(AA51*MIN(1,Inputs!$D$55/C51),0) -> 0 | AB73: =IFERROR(AB51*MIN(1,Inputs!$D$55/C51),0) -> 0 | AC73: =IFERROR(AC51*MIN(1,Inputs!$D$55/C51),0) -> 0 | AD73: =IFERROR(AD51*MIN(1,Inputs!$D$55/C51),0) -> 0 | AE73: =IFERROR(AE51*MIN(1,Inputs!$D$55/C51),0) -> 0 | AF73: =IFERROR(AF51*MIN(1,Inputs!$D$55/C51),0) -> 0 | AG73: =IFERROR(AG51*MIN(1,Inputs!$D$55/C51),0) -> 0 | AH73: =IFERROR(AH51*MIN(1,Inputs!$D$55/C51),0) -> 0 | AI73: =IFERROR(AI51*MIN(1,Inputs!$D$55/C51),0) -> 0 | AJ73: =IFERROR(AJ51*MIN(1,Inputs!$D$55/C51),0) -> 0 | AK73: =IFERROR(AK51*MIN(1,Inputs!$D$55/C51),0) -> 0 | AL73: =IFERROR(AL51*MIN(1,Inputs!$D$55/C51),0) -> 0 | AM73: =IFERROR(AM51*MIN(1,Inputs!$D$55/C51),0) -> 0 | AN73: =IFERROR(AN51*MIN(1,Inputs!$D$55/C51),0) -> 0 | AO73: =IFERROR(AO51*MIN(1,Inputs!$D$55/C51),0) -> 0 | AP73: =IFERROR(AP51*MIN(1,Inputs!$D$55/C51),0) -> 0 | AQ73: =IFERROR(AQ51*MIN(1,Inputs!$D$55/C51),0) -> 0 | AR73: =IFERROR(AR51*MIN(1,Inputs!$D$55/C51),0) -> 0 | AS73: =IFERROR(AS51*MIN(1,Inputs!$D$55/C51),0) -> 0 | AT73: =IFERROR(AT51*MIN(1,Inputs!$D$55/C51),0) -> 0 | AU73: =IFERROR(AU51*MIN(1,Inputs!$D$55/C51),0) -> 0 | AV73: =IFERROR(AV51*MIN(1,Inputs!$D$55/C51),0) -> 0 | AW73: =IFERROR(AW51*MIN(1,Inputs!$D$55/C51),0) -> 0 | AX73: =IFERROR(AX51*MIN(1,Inputs!$D$55/C51),0) -> 0 | AY73: =IFERROR(AY51*MIN(1,Inputs!$D$55/C51),0) -> 0 | AZ73: =IFERROR(AZ51*MIN(1,Inputs!$D$55/C51),0) -> 0 | BA73: =IFERROR(BA51*MIN(1,Inputs!$D$55/C51),0) -> 0 | BB73: =IFERROR(BB51*MIN(1,Inputs!$D$55/C51),0) -> 0 | BC73: =IFERROR(BC51*MIN(1,Inputs!$D$55/C51),0) -> 0 | BD73: =IFERROR(BD51*MIN(1,Inputs!$D$55/C51),0) -> 0 | BE73: =IFERROR(BE51*MIN(1,Inputs!$D$55/C51),0) -> 0 | BF73: =IFERROR(BF51*MIN(1,Inputs!$D$55/C51),0) -> 0 | BG73: =IFERROR(BG51*MIN(1,Inputs!$D$55/C51),0) -> 0 | BH73: =IFERROR(BH51*MIN(1,Inputs!$D$55/C51),0) -> 0 | BI73: =IFERROR(BI51*MIN(1,Inputs!$D$55/C51),0) -> 0 | BJ73: =IFERROR(BJ51*MIN(1,Inputs!$D$55/C51),0) -> 0 | BK73: =IFERROR(BK51*MIN(1,Inputs!$D$55/C51),0) -> 0 | BL73: =IFERROR(BL51*MIN(1,Inputs!$D$55/C51),0) -> 0 | BM73: =IFERROR(BM51*MIN(1,Inputs!$D$55/C51),0) -> 0 | BN73: =IFERROR(BN51*MIN(1,Inputs!$D$55/C51),0) -> 0 | BO73: =IFERROR(BO51*MIN(1,Inputs!$D$55/C51),0) -> 0
B74: PIK interest accrual | C74: =SUM(H74:BO74) -> #REF! | H74: =0 -> 0 | I74: =H76*(Inputs!$D$57/12) -> #REF! | J74: =I76*(Inputs!$D$57/12) -> #REF! | K74: =J76*(Inputs!$D$57/12) -> #REF! | L74: =K76*(Inputs!$D$57/12) -> #REF! | M74: =L76*(Inputs!$D$57/12) -> #REF! | N74: =M76*(Inputs!$D$57/12) -> #REF! | O74: =N76*(Inputs!$D$57/12) -> #REF! | P74: =O76*(Inputs!$D$57/12) -> #REF! | ... BO74: =BN76*(Inputs!$D$57/12) -> #REF!
B75: Principal repayment (sales sweep) | C75: =SUM(H75:BO75) -> #REF! | H75: =MIN(H55*Inputs!#REF!,H73+H72+H74) -> #REF! | I75: =MIN(I55*Inputs!#REF!,H76+I73+I72+I74) -> #REF! | J75: =MIN(J55*Inputs!#REF!,I76+J73+J72+J74) -> #REF! | K75: =MIN(K55*Inputs!#REF!,J76+K73+K72+K74) -> #REF! | L75: =MIN(L55*Inputs!#REF!,K76+L73+L72+L74) -> #REF! | M75: =MIN(M55*Inputs!#REF!,L76+M73+M72+M74) -> #REF! | N75: =MIN(N55*Inputs!#REF!,M76+N73+N72+N74) -> #REF! | O75: =MIN(O55*Inputs!#REF!,N76+O73+O72+O74) -> #REF! | P75: =MIN(P55*Inputs!#REF!,O76+P73+P72+P74) -> #REF! | ... BO75: =MIN(BO55*Inputs!#REF!,BN76+BO73+BO72+BO74) -> #REF!
B76: Loan Balance (end of month) | C76: =BO76 -> #REF! | H76: =H73+H72+H74-H75 -> #REF! | I76: =H76+I73+I72+I74-I75 -> #REF! | J76: =I76+J73+J72+J74-J75 -> #REF! | K76: =J76+K73+K72+K74-K75 -> #REF! | L76: =K76+L73+L72+L74-L75 -> #REF! | M76: =L76+M73+M72+M74-M75 -> #REF! | N76: =M76+N73+N72+N74-N75 -> #REF! | O76: =N76+O73+O72+O74-O75 -> #REF! | P76: =O76+P73+P72+P74-P75 -> #REF! | ... BO76: =BN76+BO73+BO72+BO74-BO75 -> #REF!
